{"andrea_carolina_gutierrez_valenzuela":{"2016":{"7":{"internalPath":"/Area de Educación/Año 2016/Julio","institution":"Corporación Municipal de Valparaíso","institutionCode":"CM015","publicationDate":"2021/07/29","year":2016,"monthString":"Julio","contractType":"Docente","name":"ANDREA CAROLINA","surname1":"GUTIERREZ","surname2":"VALENZUELA","salaryGrade":"No Asimilado a Grado","qualificationType":"SIN TITULO","position":"PROFESOR BASICO COMUN","region":"Región de Valparaíso","extraBenefits":"(107)(144)(133)(88)(73)(43)(143)(87)","currency":"Pesos","salaryBeforeTaxes":724760,"salaryAfterTaxes":343825,"bonusDayTime":"","extraHoursDayTime":"","bonusNightTime":"","extraHoursNightTime":"","bonusHolidays":"","extraHoursHolidays":"","startDate":"20/03/2014","endDate":"28/02/2017","obs":"Sin observaciones","link":"No","travelExpenses":"","activated":"SÍ","fullName":"ANDREA CAROLINA GUTIERREZ VALENZUELA","slug":"andrea_carolina_gutierrez_valenzuela","month":7,"cleanFullName":"andrea carolina gutierrez valenzuela"},"8":{"internalPath":"/Area de Educación/Año 2016/Agosto","institution":"Corporación Municipal de Valparaíso","institutionCode":"CM015","publicationDate":"2021/07/29","year":2016,"monthString":"Agosto","contractType":"Docente","name":"ANDREA CAROLINA","surname1":"GUTIERREZ","surname2":"VALENZUELA","salaryGrade":"No Asimilado a Grado","qualificationType":"PROFESOR EDUCACION BASICA","position":"PROFESOR BASICO COMUN","region":"Región de Valparaíso","extraBenefits":"(87)(143)(43)(73)(88)(133)(144)(107)","currency":"Pesos","salaryBeforeTaxes":724760,"salaryAfterTaxes":343825,"bonusDayTime":"","extraHoursDayTime":"","bonusNightTime":"","extraHoursNightTime":"","bonusHolidays":"","extraHoursHolidays":"","startDate":"20/03/2014","endDate":"28/02/2017","obs":"Sin observaciones","link":"No","travelExpenses":"","activated":"SÍ","fullName":"ANDREA CAROLINA GUTIERREZ VALENZUELA","slug":"andrea_carolina_gutierrez_valenzuela","month":8,"cleanFullName":"andrea carolina gutierrez valenzuela"},"9":{"internalPath":"/Area de Educación/Año 2016/Septiembre","institution":"Corporación Municipal de Valparaíso","institutionCode":"CM015","publicationDate":"2021/07/29","year":2016,"monthString":"Septiembre","contractType":"Docente","name":"ANDREA CAROLINA","surname1":"GUTIERREZ","surname2":"VALENZUELA","salaryGrade":"No Asimilado a Grado","qualificationType":"SIN TITULO","position":"PROFESOR BASICO COMUN","region":"Región de Valparaíso","extraBenefits":"(107)(144)(133)(88)(73)(43)(143)(87)","currency":"Pesos","salaryBeforeTaxes":724760,"salaryAfterTaxes":343825,"bonusDayTime":"","extraHoursDayTime":"","bonusNightTime":"","extraHoursNightTime":"","bonusHolidays":"","extraHoursHolidays":"","startDate":"20/03/2014","endDate":"28/02/2017","obs":"Sin observaciones","link":"No","travelExpenses":"","activated":"SÍ","fullName":"ANDREA CAROLINA GUTIERREZ VALENZUELA","slug":"andrea_carolina_gutierrez_valenzuela","month":9,"cleanFullName":"andrea carolina gutierrez valenzuela"},"10":{"internalPath":"/Area de Educación/Año 2016/Octubre","institution":"Corporación Municipal de Valparaíso","institutionCode":"CM015","publicationDate":"2021/07/29","year":2016,"monthString":"Octubre","contractType":"Docente","name":"ANDREA CAROLINA","surname1":"GUTIERREZ","surname2":"VALENZUELA","salaryGrade":"No Asimilado a Grado","qualificationType":"SIN TITULO","position":"PROFESOR BASICO COMUN","region":"Región de Valparaíso","extraBenefits":"(87)(143)(43)(73)(88)(133)(144)(107)","currency":"Pesos","salaryBeforeTaxes":724760,"salaryAfterTaxes":355572,"bonusDayTime":"","extraHoursDayTime":"","bonusNightTime":"","extraHoursNightTime":"","bonusHolidays":"","extraHoursHolidays":"","startDate":"20/03/2014","endDate":"28/02/2017","obs":"Sin observaciones","link":"No","travelExpenses":"","activated":"SÍ","fullName":"ANDREA CAROLINA GUTIERREZ VALENZUELA","slug":"andrea_carolina_gutierrez_valenzuela","month":10,"cleanFullName":"andrea carolina gutierrez valenzuela"},"11":{"internalPath":"/Area de Educación/Año 2016/Noviembre","institution":"Corporación Municipal de Valparaíso","institutionCode":"CM015","publicationDate":"2021/07/29","year":2016,"monthString":"Noviembre","contractType":"Docente","name":"ANDREA CAROLINA","surname1":"GUTIERREZ","surname2":"VALENZUELA","salaryGrade":"No Asimilado a Grado","qualificationType":"SIN TITULO","position":"PROFESOR BASICO COMUN","region":"Región de Valparaíso","extraBenefits":"(87)(143)(43)(73)(88)(133)(144)(107)","currency":"Pesos","salaryBeforeTaxes":724760,"salaryAfterTaxes":398247,"bonusDayTime":"","extraHoursDayTime":"","bonusNightTime":"","extraHoursNightTime":"","bonusHolidays":"","extraHoursHolidays":"","startDate":"20/03/2014","endDate":"28/02/2017","obs":"D314","link":"No","travelExpenses":"","activated":"SÍ","fullName":"ANDREA CAROLINA GUTIERREZ VALENZUELA","slug":"andrea_carolina_gutierrez_valenzuela","month":11,"cleanFullName":"andrea carolina gutierrez valenzuela"},"12":{"internalPath":"/Area de Educación/Año 2016/Diciembre","institution":"Corporación Municipal de Valparaíso","institutionCode":"CM015","publicationDate":"2021/07/29","year":2016,"monthString":"Diciembre","contractType":"Docente","name":"ANDREA CAROLINA","surname1":"GUTIERREZ","surname2":"VALENZUELA","salaryGrade":"No Asimilado a Grado","qualificationType":"SIN TITULO","position":"PROFESOR BASICO COMUN","region":"Región de Valparaíso","extraBenefits":"(107)(144)(133)(88)(73)(43)(143)(87)","currency":"Pesos","salaryBeforeTaxes":745913,"salaryAfterTaxes":415536,"bonusDayTime":"","extraHoursDayTime":"","bonusNightTime":"","extraHoursNightTime":"","bonusHolidays":"","extraHoursHolidays":"","startDate":"20/03/2014","endDate":"28/02/2017","obs":"D314","link":"No","travelExpenses":"","activated":"SÍ","fullName":"ANDREA CAROLINA GUTIERREZ VALENZUELA","slug":"andrea_carolina_gutierrez_valenzuela","month":12,"cleanFullName":"andrea carolina gutierrez valenzuela"}},"2017":{"1":{"internalPath":"/Area de Educación/Año 2017/Enero","institution":"Corporación Municipal de Valparaíso","institutionCode":"CM015","publicationDate":"2021/07/29","year":2017,"monthString":"Enero","contractType":"Docente","name":"ANDREA CAROLINA","surname1":"GUTIERREZ","surname2":"VALENZUELA","salaryGrade":"No Asimilado a Grado","qualificationType":"SIN TITULO","position":"PROFESOR BASICO COMUN","region":"Región de Valparaíso","extraBenefits":"(87)(143)(43)(73)(88)(133)(144)(107)","currency":"Pesos","salaryBeforeTaxes":745911,"salaryAfterTaxes":415534,"bonusDayTime":"","extraHoursDayTime":"","bonusNightTime":"","extraHoursNightTime":"","bonusHolidays":"","extraHoursHolidays":"","startDate":"20/03/2014","endDate":"28/02/2017","obs":"D314","link":"No","travelExpenses":"","activated":"SÍ","fullName":"ANDREA CAROLINA GUTIERREZ VALENZUELA","slug":"andrea_carolina_gutierrez_valenzuela","month":1,"cleanFullName":"andrea carolina gutierrez valenzuela"},"2":{"internalPath":"/Area de Educación/Año 2017/Febrero","institution":"Corporación Municipal de Valparaíso","institutionCode":"CM015","publicationDate":"2021/07/29","year":2017,"monthString":"Febrero","contractType":"Docente","name":"ANDREA CAROLINA","surname1":"GUTIERREZ","surname2":"VALENZUELA","salaryGrade":"No Asimilado a Grado","qualificationType":"SIN TITULO","position":"PROFESOR BASICO COMUN","region":"Región de Valparaíso","extraBenefits":"(107)(144)(133)(88)(73)(43)(143)(87)","currency":"Pesos","salaryBeforeTaxes":746511,"salaryAfterTaxes":415953,"bonusDayTime":"","extraHoursDayTime":"","bonusNightTime":"","extraHoursNightTime":"","bonusHolidays":"","extraHoursHolidays":"","startDate":"20/03/2014","endDate":"28/02/2017","obs":"D314","link":"No","travelExpenses":"","activated":"SÍ","fullName":"ANDREA CAROLINA GUTIERREZ VALENZUELA","slug":"andrea_carolina_gutierrez_valenzuela","month":2,"cleanFullName":"andrea carolina gutierrez valenzuela"},"3":{"internalPath":"/Area de Educación/Año 2017/Marzo","institution":"Corporación Municipal de Valparaíso","institutionCode":"CM015","publicationDate":"2021/07/29","year":2017,"monthString":"Marzo","contractType":"Docente","name":"ANDREA CAROLINA","surname1":"GUTIERREZ","surname2":"VALENZUELA","salaryGrade":"No Asimilado a Grado","qualificationType":"PROFESOR BASICO COMUN","position":"PROFESOR BASICO COMUN","region":"Región de Valparaíso","extraBenefits":"(87)(43)(73)(88)(107)","currency":"Pesos","salaryBeforeTaxes":516636,"salaryAfterTaxes":205698,"bonusDayTime":"","extraHoursDayTime":"","bonusNightTime":"","extraHoursNightTime":"","bonusHolidays":"","extraHoursHolidays":"","startDate":"20/03/2014","endDate":"28/02/2018","obs":"D314","link":"No","travelExpenses":"","activated":"SÍ","fullName":"ANDREA CAROLINA GUTIERREZ VALENZUELA","slug":"andrea_carolina_gutierrez_valenzuela","month":3,"cleanFullName":"andrea carolina gutierrez valenzuela"},"4":{"internalPath":"/Area de Educación/Año 2017/Abril","institution":"Corporación Municipal de Valparaíso","institutionCode":"CM015","publicationDate":"2021/07/29","year":2017,"monthString":"Abril","contractType":"Docente","name":"ANDREA CAROLINA","surname1":"GUTIERREZ","surname2":"VALENZUELA","salaryGrade":"No Asimilado a Grado","qualificationType":"PROFESOR BASICO COMUN","position":"PROFESOR BASICO COMUN","region":"Región de Valparaíso","extraBenefits":"(107)(88)(73)(43)(87)","currency":"Pesos","salaryBeforeTaxes":516636,"salaryAfterTaxes":205698,"bonusDayTime":"","extraHoursDayTime":"","bonusNightTime":"","extraHoursNightTime":"","bonusHolidays":"","extraHoursHolidays":"","startDate":"20/03/2014","endDate":"28/02/2018","obs":"D314","link":"No","travelExpenses":"","activated":"SÍ","fullName":"ANDREA CAROLINA GUTIERREZ VALENZUELA","slug":"andrea_carolina_gutierrez_valenzuela","month":4,"cleanFullName":"andrea carolina gutierrez valenzuela"},"5":{"internalPath":"/Area de Educación/Año 2017/Mayo","institution":"Corporación Municipal de Valparaíso","institutionCode":"CM015","publicationDate":"2021/07/29","year":2017,"monthString":"Mayo","contractType":"Docente","name":"ANDREA CAROLINA","surname1":"GUTIERREZ","surname2":"VALENZUELA","salaryGrade":"No Asimilado a Grado","qualificationType":"PROFESOR BASICO COMUN","position":"PROFESOR BASICO COMUN","region":"Región de Valparaíso","extraBenefits":"(87)(143)(43)(73)(88)(133)(107)","currency":"Pesos","salaryBeforeTaxes":544234,"salaryAfterTaxes":228207,"bonusDayTime":"","extraHoursDayTime":"","bonusNightTime":"","extraHoursNightTime":"","bonusHolidays":"","extraHoursHolidays":"","startDate":"20/03/2014","endDate":"28/02/2018","obs":"D314","link":"No","travelExpenses":"","activated":"SÍ","fullName":"ANDREA CAROLINA GUTIERREZ VALENZUELA","slug":"andrea_carolina_gutierrez_valenzuela","month":5,"cleanFullName":"andrea carolina gutierrez valenzuela"},"6":{"internalPath":"/Area de Educación/Año 2017/Junio","institution":"Corporación Municipal de Valparaíso","institutionCode":"CM015","publicationDate":"2021/07/29","year":2017,"monthString":"Junio","contractType":"Docente","name":"ANDREA CAROLINA","surname1":"GUTIERREZ","surname2":"VALENZUELA","salaryGrade":"No Asimilado a Grado","qualificationType":"PROFESOR BASICO COMUN","position":"PROFESOR BASICO COMUN","region":"Región de Valparaíso","extraBenefits":"(107)(133)(88)(73)(43)(143)(87)","currency":"Pesos","salaryBeforeTaxes":558917,"salaryAfterTaxes":240182,"bonusDayTime":"","extraHoursDayTime":"","bonusNightTime":"","extraHoursNightTime":"","bonusHolidays":"","extraHoursHolidays":"","startDate":"20/03/2014","endDate":"28/02/2018","obs":"D314","link":"No","travelExpenses":"","activated":"SÍ","fullName":"ANDREA CAROLINA GUTIERREZ VALENZUELA","slug":"andrea_carolina_gutierrez_valenzuela","month":6,"cleanFullName":"andrea carolina gutierrez valenzuela"},"7":{"internalPath":"/Area de Educación/Año 2017/Julio","institution":"Corporación Municipal de Valparaíso","institutionCode":"CM015","publicationDate":"2021/07/29","year":2017,"monthString":"Julio","contractType":"Docente","name":"ANDREA CAROLINA","surname1":"GUTIERREZ","surname2":"VALENZUELA","salaryGrade":"No Asimilado a Grado","qualificationType":"PROFESOR BASICO COMUN","position":"PROFESOR BASICO COMUN","region":"Región de Valparaíso","extraBenefits":"(87)(143)(73)(122)(107)(95)","currency":"Pesos","salaryBeforeTaxes":741264,"salaryAfterTaxes":389300,"bonusDayTime":"","extraHoursDayTime":"","bonusNightTime":"","extraHoursNightTime":"","bonusHolidays":"","extraHoursHolidays":"","startDate":"20/03/2014","endDate":"28/02/2018","obs":"D314","link":"No","travelExpenses":"","activated":"SÍ","fullName":"ANDREA CAROLINA GUTIERREZ VALENZUELA","slug":"andrea_carolina_gutierrez_valenzuela","month":7,"cleanFullName":"andrea carolina gutierrez valenzuela"},"8":{"internalPath":"/Area de Educación/Año 2017/Agosto","institution":"Corporación Municipal de Valparaíso","institutionCode":"CM015","publicationDate":"2021/07/29","year":2017,"monthString":"Agosto","contractType":"Docente","name":"ANDREA CAROLINA","surname1":"GUTIERREZ","surname2":"VALENZUELA","salaryGrade":"No Asimilado a Grado","qualificationType":"PROFESOR BASICO COMUN","position":"PROFESOR BASICO COMUN","region":"Región de Valparaíso","extraBenefits":"(95)(107)(122)(73)(143)(87)","currency":"Pesos","salaryBeforeTaxes":679559,"salaryAfterTaxes":338975,"bonusDayTime":"","extraHoursDayTime":"","bonusNightTime":"","extraHoursNightTime":"","bonusHolidays":"","extraHoursHolidays":"","startDate":"20/03/2014","endDate":"28/02/2018","obs":"D314","link":"No","travelExpenses":"","activated":"SÍ","fullName":"ANDREA CAROLINA GUTIERREZ VALENZUELA","slug":"andrea_carolina_gutierrez_valenzuela","month":8,"cleanFullName":"andrea carolina gutierrez valenzuela"},"9":{"internalPath":"/Area de Educación/Año 2017/Septiembre","institution":"Corporación Municipal de Valparaíso","institutionCode":"CM015","publicationDate":"2021/07/29","year":2017,"monthString":"Septiembre","contractType":"Docente","name":"ANDREA CAROLINA","surname1":"GUTIERREZ","surname2":"VALENZUELA","salaryGrade":"No Asimilado a Grado","qualificationType":"PROFESOR BASICO COMUN","position":"PROFESOR BASICO COMUN","region":"Región de Valparaíso","extraBenefits":"(87)(143)(73)(122)(107)(95)","currency":"Pesos","salaryBeforeTaxes":679559,"salaryAfterTaxes":338985,"bonusDayTime":"","extraHoursDayTime":"","bonusNightTime":"","extraHoursNightTime":"","bonusHolidays":"","extraHoursHolidays":"","startDate":"20/03/2014","endDate":"28/02/2018","obs":"D314","link":"No","travelExpenses":"","activated":"SÍ","fullName":"ANDREA CAROLINA GUTIERREZ VALENZUELA","slug":"andrea_carolina_gutierrez_valenzuela","month":9,"cleanFullName":"andrea carolina gutierrez valenzuela"},"10":{"internalPath":"/Area de Educación/Año 2017/Octubre","institution":"Corporación Municipal de Valparaíso","institutionCode":"CM015","publicationDate":"2021/07/29","year":2017,"monthString":"Octubre","contractType":"Docente","name":"ANDREA CAROLINA","surname1":"GUTIERREZ","surname2":"VALENZUELA","salaryGrade":"No Asimilado a Grado","qualificationType":"SIN TITULO","position":"PROFESOR BASICO COMUN","region":"Región de Valparaíso","extraBenefits":"(95)(107)(122)(73)(143)(87)","currency":"Pesos","salaryBeforeTaxes":679559,"salaryAfterTaxes":474525,"bonusDayTime":"","extraHoursDayTime":"","bonusNightTime":"","extraHoursNightTime":"","bonusHolidays":"","extraHoursHolidays":"","startDate":"20/03/2014","endDate":"28/02/2018","obs":"D314","link":"No","travelExpenses":"","activated":"SÍ","fullName":"ANDREA CAROLINA GUTIERREZ VALENZUELA","slug":"andrea_carolina_gutierrez_valenzuela","month":10,"cleanFullName":"andrea carolina gutierrez valenzuela"},"11":{"internalPath":"/Area de Educación/Año 2017/Noviembre","institution":"Corporación Municipal de Valparaíso","institutionCode":"CM015","publicationDate":"2021/07/29","year":2017,"monthString":"Noviembre","contractType":"Docente","name":"ANDREA CAROLINA","surname1":"GUTIERREZ","surname2":"VALENZUELA","salaryGrade":"No Asimilado a Grado","qualificationType":"SIN TITULO","position":"PROFESOR BASICO COMUN","region":"Región de Valparaíso","extraBenefits":"(87)(143)(73)(122)(107)(95)","currency":"Pesos","salaryBeforeTaxes":679559,"salaryAfterTaxes":431150,"bonusDayTime":"","extraHoursDayTime":"","bonusNightTime":"","extraHoursNightTime":"","bonusHolidays":"","extraHoursHolidays":"","startDate":"20/03/2014","endDate":"28/02/2018","obs":"D314","link":"No","travelExpenses":"","activated":"SÍ","fullName":"ANDREA CAROLINA GUTIERREZ VALENZUELA","slug":"andrea_carolina_gutierrez_valenzuela","month":11,"cleanFullName":"andrea carolina gutierrez valenzuela"},"12":{"internalPath":"/Area de Educación/Año 2017/Diciembre","institution":"Corporación Municipal de Valparaíso","institutionCode":"CM015","publicationDate":"2021/07/29","year":2017,"monthString":"Diciembre","contractType":"Docente","name":"ANDREA CAROLINA","surname1":"GUTIERREZ","surname2":"VALENZUELA","salaryGrade":"No Asimilado a Grado","qualificationType":"SIN TITULO","position":"PROFESOR BASICO COMUN","region":"Región de Valparaíso","extraBenefits":"(95)(107)(122)(73)(143)(87)","currency":"Pesos","salaryBeforeTaxes":696487,"salaryAfterTaxes":302560,"bonusDayTime":"","extraHoursDayTime":"","bonusNightTime":"","extraHoursNightTime":"","bonusHolidays":"","extraHoursHolidays":"","startDate":"20/03/2014","endDate":"28/02/2018","obs":"D314","link":"No","travelExpenses":"","activated":"SÍ","fullName":"ANDREA CAROLINA GUTIERREZ VALENZUELA","slug":"andrea_carolina_gutierrez_valenzuela","month":12,"cleanFullName":"andrea carolina gutierrez valenzuela"}},"2018":{"1":{"internalPath":"/Area de Educación/Año 2018/Enero","institution":"Corporación Municipal de Valparaíso","institutionCode":"CM015","publicationDate":"2021/07/29","year":2018,"monthString":"Enero","contractType":"Docente","name":"ANDREA CAROLINA","surname1":"GUTIERREZ","surname2":"VALENZUELA","salaryGrade":"No Asimilado a Grado","qualificationType":"SIN TITULO","position":"PROFESOR BASICO COMUN","region":"Región de Valparaíso","extraBenefits":"(95)(107)(122)(73)(143)(87)","currency":"Pesos","salaryBeforeTaxes":828310,"salaryAfterTaxes":523614,"bonusDayTime":"","extraHoursDayTime":"","bonusNightTime":"","extraHoursNightTime":"","bonusHolidays":"","extraHoursHolidays":"","startDate":"20/03/2014","endDate":"28/02/2018","obs":"D314","link":"No","travelExpenses":"","activated":"SÍ","fullName":"ANDREA CAROLINA GUTIERREZ VALENZUELA","slug":"andrea_carolina_gutierrez_valenzuela","month":1,"cleanFullName":"andrea carolina gutierrez valenzuela"},"2":{"internalPath":"/Area de Educación/Año 2018/Febrero","institution":"Corporación Municipal de Valparaíso","institutionCode":"CM015","publicationDate":"2021/07/29","year":2018,"monthString":"Febrero","contractType":"Docente","name":"ANDREA CAROLINA","surname1":"GUTIERREZ","surname2":"VALENZUELA","salaryGrade":"No Asimilado a Grado","qualificationType":"SIN TITULO","position":"PROFESOR BASICO COMUN","region":"Región de Valparaíso","extraBenefits":"(87)(143)(73)(122)(107)(95)","currency":"Pesos","salaryBeforeTaxes":696535,"salaryAfterTaxes":401934,"bonusDayTime":"","extraHoursDayTime":"","bonusNightTime":"","extraHoursNightTime":"","bonusHolidays":"","extraHoursHolidays":"","startDate":"20/03/2014","endDate":"28/02/2018","obs":"D314","link":"No","travelExpenses":"","activated":"SÍ","fullName":"ANDREA CAROLINA GUTIERREZ VALENZUELA","slug":"andrea_carolina_gutierrez_valenzuela","month":2,"cleanFullName":"andrea carolina gutierrez valenzuela"},"3":{"internalPath":"/Area de Educación/Año 2018/Marzo","institution":"Corporación Municipal de Valparaíso","institutionCode":"CM015","publicationDate":"2021/07/29","year":2018,"monthString":"Marzo","contractType":"Docente","name":"ANDREA CAROLINA","surname1":"GUTIERREZ","surname2":"VALENZUELA","salaryGrade":"No Asimilado a Grado","qualificationType":"SIN TITULO","position":"PROFESOR BASICO COMUN","region":"Región de Valparaíso","extraBenefits":"(95)(107)(122)(73)(15)(87)","currency":"Pesos","salaryBeforeTaxes":754317,"salaryAfterTaxes":449061,"bonusDayTime":"","extraHoursDayTime":"","bonusNightTime":"","extraHoursNightTime":"","bonusHolidays":"","extraHoursHolidays":"","startDate":"20/03/2014","endDate":"28/02/2019","obs":"D314","link":"No","travelExpenses":"","activated":"SÍ","fullName":"ANDREA CAROLINA GUTIERREZ VALENZUELA","slug":"andrea_carolina_gutierrez_valenzuela","month":3,"cleanFullName":"andrea carolina gutierrez valenzuela"},"4":{"internalPath":"/Area de Educación/Año 2018/Abril","institution":"Corporación Municipal de Valparaíso","institutionCode":"CM015","publicationDate":"2021/07/29","year":2018,"monthString":"Abril","contractType":"Docente","name":"ANDREA CAROLINA","surname1":"GUTIERREZ","surname2":"VALENZUELA","salaryGrade":"No Asimilado a Grado","qualificationType":"SIN TITULO","position":"PROFESOR BASICO COMUN","region":"Región de Valparaíso","extraBenefits":"(87)(15)(73)(122)(107)(95)","currency":"Pesos","salaryBeforeTaxes":754317,"salaryAfterTaxes":449061,"bonusDayTime":"","extraHoursDayTime":"","bonusNightTime":"","extraHoursNightTime":"","bonusHolidays":"","extraHoursHolidays":"","startDate":"20/03/2014","endDate":"28/02/2019","obs":"D314","link":"No","travelExpenses":"","activated":"SÍ","fullName":"ANDREA CAROLINA GUTIERREZ VALENZUELA","slug":"andrea_carolina_gutierrez_valenzuela","month":4,"cleanFullName":"andrea carolina gutierrez valenzuela"},"5":{"internalPath":"/Area de Educación/Año 2018/Mayo","institution":"Corporación Municipal de Valparaíso","institutionCode":"CM015","publicationDate":"2021/07/29","year":2018,"monthString":"Mayo","contractType":"Docente","name":"ANDREA CAROLINA","surname1":"GUTIERREZ","surname2":"VALENZUELA","salaryGrade":"No Asimilado a Grado","qualificationType":"SIN TITULO","position":"PROFESOR BASICO COMUN","region":"Región de Valparaíso","extraBenefits":"(87)(15)(73)(122)(107)(95)","currency":"Pesos","salaryBeforeTaxes":754317,"salaryAfterTaxes":449061,"bonusDayTime":"","extraHoursDayTime":"","bonusNightTime":"","extraHoursNightTime":"","bonusHolidays":"","extraHoursHolidays":"","startDate":"20/03/2014","endDate":"28/02/2019","obs":"D314","link":"No","travelExpenses":"","activated":"SÍ","fullName":"ANDREA CAROLINA GUTIERREZ VALENZUELA","slug":"andrea_carolina_gutierrez_valenzuela","month":5,"cleanFullName":"andrea carolina gutierrez valenzuela"},"6":{"internalPath":"/Area de Educación/Año 2018/Junio","institution":"Corporación Municipal de Valparaíso","institutionCode":"CM015","publicationDate":"2021/07/29","year":2018,"monthString":"Junio","contractType":"Docente","name":"ANDREA CAROLINA","surname1":"GUTIERREZ","surname2":"VALENZUELA","salaryGrade":"No Asimilado a Grado","qualificationType":"SIN TITULO","position":"PROFESOR BASICO COMUN","region":"Región de Valparaíso","extraBenefits":"(95)(107)(122)(73)(15)(87)","currency":"Pesos","salaryBeforeTaxes":754317,"salaryAfterTaxes":449061,"bonusDayTime":"","extraHoursDayTime":"","bonusNightTime":"","extraHoursNightTime":"","bonusHolidays":"","extraHoursHolidays":"","startDate":"20/03/2014","endDate":"28/02/2019","obs":"D314","link":"No","travelExpenses":"","activated":"SÍ","fullName":"ANDREA CAROLINA GUTIERREZ VALENZUELA","slug":"andrea_carolina_gutierrez_valenzuela","month":6,"cleanFullName":"andrea carolina gutierrez valenzuela"},"7":{"internalPath":"/Area de Educación/Año 2018/Julio","institution":"Corporación Municipal de Valparaíso","institutionCode":"CM015","publicationDate":"2021/07/29","year":2018,"monthString":"Julio","contractType":"Docente","name":"ANDREA CAROLINA","surname1":"GUTIERREZ","surname2":"VALENZUELA","salaryGrade":"No Asimilado a Grado","qualificationType":"SIN TITULO","position":"PROFESOR BASICO COMUN","region":"Región de Valparaíso","extraBenefits":"(87)(15)(73)(122)(17)(95)","currency":"Pesos","salaryBeforeTaxes":778940,"salaryAfterTaxes":469143,"bonusDayTime":"","extraHoursDayTime":"","bonusNightTime":"","extraHoursNightTime":"","bonusHolidays":"","extraHoursHolidays":"","startDate":"20/03/2014","endDate":"28/02/2019","obs":"D314","link":"No","travelExpenses":"","activated":"SÍ","fullName":"ANDREA CAROLINA GUTIERREZ VALENZUELA","slug":"andrea_carolina_gutierrez_valenzuela","month":7,"cleanFullName":"andrea carolina gutierrez valenzuela"},"8":{"internalPath":"/Area de Educación/Año 2018/Agosto","institution":"Corporación Municipal de Valparaíso","institutionCode":"CM015","publicationDate":"2021/07/29","year":2018,"monthString":"Agosto","contractType":"Docente","name":"ANDREA CAROLINA","surname1":"GUTIERREZ","surname2":"VALENZUELA","salaryGrade":"No Asimilado a Grado","qualificationType":"SIN TITULO","position":"PROFESOR BASICO COMUN","region":"Región de Valparaíso","extraBenefits":"(95)(107)(122)(73)(15)(87)","currency":"Pesos","salaryBeforeTaxes":778940,"salaryAfterTaxes":465532,"bonusDayTime":"","extraHoursDayTime":"","bonusNightTime":"","extraHoursNightTime":"","bonusHolidays":"","extraHoursHolidays":"","startDate":"20/03/2014","endDate":"28/02/2019","obs":"D314","link":"No","travelExpenses":"","activated":"SÍ","fullName":"ANDREA CAROLINA GUTIERREZ VALENZUELA","slug":"andrea_carolina_gutierrez_valenzuela","month":8,"cleanFullName":"andrea carolina gutierrez valenzuela"},"9":{"internalPath":"/Area de Educación/Año 2018/Septiembre","institution":"Corporación Municipal de Valparaíso","institutionCode":"CM015","publicationDate":"2021/07/29","year":2018,"monthString":"Septiembre","contractType":"Docente","name":"ANDREA CAROLINA","surname1":"GUTIERREZ","surname2":"VALENZUELA","salaryGrade":"No Asimilado a Grado","qualificationType":"SIN TITULO","position":"PROFESOR BASICO COMUN","region":"Región de Valparaíso","extraBenefits":"(87)(15)(73)(122)(107)(95)","currency":"Pesos","salaryBeforeTaxes":776741,"salaryAfterTaxes":466944,"bonusDayTime":"","extraHoursDayTime":"","bonusNightTime":"","extraHoursNightTime":"","bonusHolidays":"","extraHoursHolidays":"","startDate":"20/03/2014","endDate":"28/02/2019","obs":"D314","link":"No","travelExpenses":"","activated":"SÍ","fullName":"ANDREA CAROLINA GUTIERREZ VALENZUELA","slug":"andrea_carolina_gutierrez_valenzuela","month":9,"cleanFullName":"andrea carolina gutierrez valenzuela"},"10":{"internalPath":"/Area de Educación/Año 2018/Octubre","institution":"Corporación Municipal de Valparaíso","institutionCode":"CM015","publicationDate":"2021/07/29","year":2018,"monthString":"Octubre","contractType":"Docente","name":"ANDREA CAROLINA","surname1":"GUTIERREZ","surname2":"VALENZUELA","salaryGrade":"No Asimilado a Grado","qualificationType":"SIN TITULO","position":"PROFESOR BASICO COMUN","region":"Región de Valparaíso","extraBenefits":"(95)(107)(122)(73)(15)(87)","currency":"Pesos","salaryBeforeTaxes":776741,"salaryAfterTaxes":461038,"bonusDayTime":"","extraHoursDayTime":"","bonusNightTime":"","extraHoursNightTime":"","bonusHolidays":"","extraHoursHolidays":"","startDate":"20/03/2014","endDate":"28/02/2019","obs":"D314","link":"No","travelExpenses":"","activated":"SÍ","fullName":"ANDREA CAROLINA GUTIERREZ VALENZUELA","slug":"andrea_carolina_gutierrez_valenzuela","month":10,"cleanFullName":"andrea carolina gutierrez valenzuela"},"11":{"internalPath":"/Area de Educación/Año 2018/Noviembre","institution":"Corporación Municipal de Valparaíso","institutionCode":"CM015","publicationDate":"2021/07/29","year":2018,"monthString":"Noviembre","contractType":"Docente","name":"ANDREA CAROLINA","surname1":"GUTIERREZ","surname2":"VALENZUELA","salaryGrade":"No Asimilado a Grado","qualificationType":"SIN TITULO","position":"PROFESOR BASICO COMUN","region":"Región de Valparaíso","extraBenefits":"(87)(15)(73)(122)(107)(95)","currency":"Pesos","salaryBeforeTaxes":776741,"salaryAfterTaxes":466944,"bonusDayTime":"","extraHoursDayTime":"","bonusNightTime":"","extraHoursNightTime":"","bonusHolidays":"","extraHoursHolidays":"","startDate":"20/03/2014","endDate":"28/02/2019","obs":"D314","link":"No","travelExpenses":"","activated":"SÍ","fullName":"ANDREA CAROLINA GUTIERREZ VALENZUELA","slug":"andrea_carolina_gutierrez_valenzuela","month":11,"cleanFullName":"andrea carolina gutierrez valenzuela"},"12":{"internalPath":"/Area de Educación/Año 2018/Diciembre","institution":"Corporación Municipal de Valparaíso","institutionCode":"CM015","publicationDate":"2021/07/29","year":2018,"monthString":"Diciembre","contractType":"Docente","name":"ANDREA CAROLINA","surname1":"GUTIERREZ","surname2":"VALENZUELA","salaryGrade":"No Asimilado a Grado","qualificationType":"SIN TITULO","position":"PROFESOR BASICO COMUN","region":"Región de Valparaíso","extraBenefits":"(95)(107)(122)(73)(15)(87)","currency":"Pesos","salaryBeforeTaxes":988899,"salaryAfterTaxes":670399,"bonusDayTime":"","extraHoursDayTime":"","bonusNightTime":"","extraHoursNightTime":"","bonusHolidays":"","extraHoursHolidays":"","startDate":"20/03/2014","endDate":"28/02/2019","obs":"D314","link":"No","travelExpenses":"","activated":"SÍ","fullName":"ANDREA CAROLINA GUTIERREZ VALENZUELA","slug":"andrea_carolina_gutierrez_valenzuela","month":12,"cleanFullName":"andrea carolina gutierrez valenzuela"}},"2019":{"1":{"internalPath":"/Area de Educación/Año 2019/Enero","institution":"Corporación Municipal de Valparaíso","institutionCode":"CM015","publicationDate":"2021/07/29","year":2019,"monthString":"Enero","contractType":"Docente","name":"ANDREA CAROLINA","surname1":"GUTIERREZ","surname2":"VALENZUELA","salaryGrade":"No Asimilado a Grado","qualificationType":"SIN TITULO","position":"PROFESOR BASICO COMUN","region":"Región de Valparaíso","extraBenefits":"(87)(15)(73)(122)(107)(95)","currency":"Pesos","salaryBeforeTaxes":922900,"salaryAfterTaxes":613368,"bonusDayTime":"","extraHoursDayTime":"","bonusNightTime":"","extraHoursNightTime":"","bonusHolidays":"","extraHoursHolidays":"","startDate":"20/03/2014","endDate":"28/02/2019","obs":"D314","link":"No","travelExpenses":"","activated":"SÍ","fullName":"ANDREA CAROLINA GUTIERREZ VALENZUELA","slug":"andrea_carolina_gutierrez_valenzuela","month":1,"cleanFullName":"andrea carolina gutierrez valenzuela"},"2":{"internalPath":"/Area de Educación/Año 2019/Febrero","institution":"Corporación Municipal de Valparaíso","institutionCode":"CM015","publicationDate":"2021/07/29","year":2019,"monthString":"Febrero","contractType":"Docente","name":"ANDREA CAROLINA","surname1":"GUTIERREZ","surname2":"VALENZUELA","salaryGrade":"No Asimilado a Grado","qualificationType":"SIN TITULO","position":"PROFESOR BASICO COMUN","region":"Región de Valparaíso","extraBenefits":"(87)(15)(73)(122)(107)(95)","currency":"Pesos","salaryBeforeTaxes":803900,"salaryAfterTaxes":494272,"bonusDayTime":"","extraHoursDayTime":"","bonusNightTime":"","extraHoursNightTime":"","bonusHolidays":"","extraHoursHolidays":"","startDate":"20/03/2014","endDate":"28/02/2019","obs":"D314","link":"No","travelExpenses":"","activated":"SÍ","fullName":"ANDREA CAROLINA GUTIERREZ VALENZUELA","slug":"andrea_carolina_gutierrez_valenzuela","month":2,"cleanFullName":"andrea carolina gutierrez valenzuela"},"3":{"internalPath":"/Area de Educación/Año 2019/Marzo","institution":"Corporación Municipal de Valparaíso","institutionCode":"CM015","publicationDate":"2021/07/29","year":2019,"monthString":"Marzo","contractType":"Docente","name":"ANDREA CAROLINA","surname1":"GUTIERREZ","surname2":"VALENZUELA","salaryGrade":"No Asimilado a Grado","qualificationType":"SIN TITULO","position":"PROFESOR BASICO COMUN","region":"Región de Valparaíso","extraBenefits":"(95)(107)(122)(73)(15)(87)","currency":"Pesos","salaryBeforeTaxes":988415,"salaryAfterTaxes":639956,"bonusDayTime":"","extraHoursDayTime":"","bonusNightTime":"","extraHoursNightTime":"","bonusHolidays":"","extraHoursHolidays":"","startDate":"20/03/2014","endDate":"29/02/2020","obs":"D314","link":"No","travelExpenses":"","activated":"SÍ","fullName":"ANDREA CAROLINA GUTIERREZ VALENZUELA","slug":"andrea_carolina_gutierrez_valenzuela","month":3,"cleanFullName":"andrea carolina gutierrez valenzuela"},"4":{"internalPath":"/Area de Educación/Año 2019/Abril","institution":"Corporación Municipal de Valparaíso","institutionCode":"CM015","publicationDate":"2021/07/29","year":2019,"monthString":"Abril","contractType":"Docente","name":"ANDREA CAROLINA","surname1":"GUTIERREZ","surname2":"VALENZUELA","salaryGrade":"No Asimilado a Grado","qualificationType":"SIN TITULO","position":"PROFESOR BASICO COMUN","region":"Región de Valparaíso","extraBenefits":"(87)(15)(73)(122)(107)(95)","currency":"Pesos","salaryBeforeTaxes":1038558,"salaryAfterTaxes":679539,"bonusDayTime":"","extraHoursDayTime":"","bonusNightTime":"","extraHoursNightTime":"","bonusHolidays":"","extraHoursHolidays":"","startDate":"20/03/2014","endDate":"29/02/2020","obs":"D314","link":"No","travelExpenses":"","activated":"SÍ","fullName":"ANDREA CAROLINA GUTIERREZ VALENZUELA","slug":"andrea_carolina_gutierrez_valenzuela","month":4,"cleanFullName":"andrea carolina gutierrez valenzuela"},"5":{"internalPath":"/Area de Educación/Año 2019/Mayo","institution":"Corporación Municipal de Valparaíso","institutionCode":"CM015","publicationDate":"2021/07/29","year":2019,"monthString":"Mayo","contractType":"Docente","name":"ANDREA CAROLINA","surname1":"GUTIERREZ","surname2":"VALENZUELA","salaryGrade":"No Asimilado a Grado","qualificationType":"SIN TITULO","position":"PROFESOR BASICO COMUN","region":"Región de Valparaíso","extraBenefits":"(95)(107)(122)(73)(15)(87)","currency":"Pesos","salaryBeforeTaxes":1038558,"salaryAfterTaxes":679539,"bonusDayTime":"","extraHoursDayTime":"","bonusNightTime":"","extraHoursNightTime":"","bonusHolidays":"","extraHoursHolidays":"","startDate":"20/03/2014","endDate":"29/02/2020","obs":"D314","link":"No","travelExpenses":"","activated":"SÍ","fullName":"ANDREA CAROLINA GUTIERREZ VALENZUELA","slug":"andrea_carolina_gutierrez_valenzuela","month":5,"cleanFullName":"andrea carolina gutierrez valenzuela"},"6":{"internalPath":"/Area de Educación/Año 2019/Junio","institution":"Corporación Municipal de Valparaíso","institutionCode":"CM015","publicationDate":"2021/07/29","year":2019,"monthString":"Junio","contractType":"Docente","name":"ANDREA CAROLINA","surname1":"GUTIERREZ","surname2":"VALENZUELA","salaryGrade":"No Asimilado a Grado","qualificationType":"SIN TITULO","position":"PROFESOR BASICO COMUN","region":"Región de Valparaíso","extraBenefits":"(87)(15)(73)(122)(107)(95)","currency":"Pesos","salaryBeforeTaxes":1038558,"salaryAfterTaxes":679748,"bonusDayTime":"","extraHoursDayTime":"","bonusNightTime":"","extraHoursNightTime":"","bonusHolidays":"","extraHoursHolidays":"","startDate":"20/03/2014","endDate":"29/02/2020","obs":"D314","link":"No","travelExpenses":"","activated":"SÍ","fullName":"ANDREA CAROLINA GUTIERREZ VALENZUELA","slug":"andrea_carolina_gutierrez_valenzuela","month":6,"cleanFullName":"andrea carolina gutierrez valenzuela"},"7":{"internalPath":"/Area de Educación/Año 2019/Julio","institution":"Corporación Municipal de Valparaíso","institutionCode":"CM015","publicationDate":"2021/07/29","year":2019,"monthString":"Julio","contractType":"Docente","name":"ANDREA CAROLINA","surname1":"GUTIERREZ","surname2":"VALENZUELA","salaryGrade":"No Asimilado a Grado","qualificationType":"SIN TITULO","position":"PROFESOR BASICO COMUN","region":"Región de Valparaíso","extraBenefits":"(95)(107)(122)(73)(15)(87)","currency":"Pesos","salaryBeforeTaxes":1038558,"salaryAfterTaxes":679906,"bonusDayTime":"","extraHoursDayTime":"","bonusNightTime":"","extraHoursNightTime":"","bonusHolidays":"","extraHoursHolidays":"","startDate":"20/03/2014","endDate":"29/02/2020","obs":"D314","link":"No","travelExpenses":"","activated":"SÍ","fullName":"ANDREA CAROLINA GUTIERREZ VALENZUELA","slug":"andrea_carolina_gutierrez_valenzuela","month":7,"cleanFullName":"andrea carolina gutierrez valenzuela"},"8":{"internalPath":"/Area de Educación/Año 2019/Agosto","institution":"Corporación Municipal de Valparaíso","institutionCode":"CM015","publicationDate":"2021/07/29","year":2019,"monthString":"Agosto","contractType":"Docente","name":"ANDREA CAROLINA","surname1":"GUTIERREZ","surname2":"VALENZUELA","salaryGrade":"No Asimilado a Grado","qualificationType":"SIN TITULO","position":"PROFESOR BASICO COMUN","region":"Región de Valparaíso","extraBenefits":"(87)(15)(73)(122)(107)(95)","currency":"Pesos","salaryBeforeTaxes":1038558,"salaryAfterTaxes":656146,"bonusDayTime":"","extraHoursDayTime":"","bonusNightTime":"","extraHoursNightTime":"","bonusHolidays":"","extraHoursHolidays":"","startDate":"20/03/2014","endDate":"29/02/2020","obs":"D314","link":"No","travelExpenses":"","activated":"SÍ","fullName":"ANDREA CAROLINA GUTIERREZ VALENZUELA","slug":"andrea_carolina_gutierrez_valenzuela","month":8,"cleanFullName":"andrea carolina gutierrez valenzuela"},"9":{"internalPath":"/Area de Educación/Año 2019/Septiembre","institution":"Corporación Municipal de Valparaíso","institutionCode":"CM015","publicationDate":"2021/07/29","year":2019,"monthString":"Septiembre","contractType":"Docente","name":"ANDREA CAROLINA","surname1":"GUTIERREZ","surname2":"VALENZUELA","salaryGrade":"No Asimilado a Grado","qualificationType":"SIN TITULO","position":"PROFESOR BASICO COMUN","region":"Región de Valparaíso","extraBenefits":"(95)(107)(122)(73)(15)(87)","currency":"Pesos","salaryBeforeTaxes":1038558,"salaryAfterTaxes":656199,"bonusDayTime":"","extraHoursDayTime":"","bonusNightTime":"","extraHoursNightTime":"","bonusHolidays":"","extraHoursHolidays":"","startDate":"20/03/2014","endDate":"29/02/2020","obs":"D314","link":"No","travelExpenses":"","activated":"SÍ","fullName":"ANDREA CAROLINA GUTIERREZ VALENZUELA","slug":"andrea_carolina_gutierrez_valenzuela","month":9,"cleanFullName":"andrea carolina gutierrez valenzuela"},"10":{"internalPath":"/Area de Educación/Año 2019/Octubre","institution":"Corporación Municipal de Valparaíso","institutionCode":"CM015","publicationDate":"2021/07/29","year":2019,"monthString":"Octubre","contractType":"Docente","name":"ANDREA CAROLINA","surname1":"GUTIERREZ","surname2":"VALENZUELA","salaryGrade":"No Asimilado a Grado","qualificationType":"SIN TITULO","position":"PROFESOR BASICO COMUN","region":"Región de Valparaíso","extraBenefits":"(87)(15)(73)(122)(107)(95)","currency":"Pesos","salaryBeforeTaxes":1038558,"salaryAfterTaxes":592847,"bonusDayTime":0,"extraHoursDayTime":0,"bonusNightTime":"","extraHoursNightTime":"","bonusHolidays":"","extraHoursHolidays":"","startDate":"20/03/2014","endDate":"29/02/2020","obs":"D314","link":"No","travelExpenses":"","activated":"SÍ","fullName":"ANDREA CAROLINA GUTIERREZ VALENZUELA","slug":"andrea_carolina_gutierrez_valenzuela","month":10,"cleanFullName":"andrea carolina gutierrez valenzuela"},"11":{"internalPath":"/Area de Educación/Año 2019/Noviembre","institution":"Corporación Municipal de Valparaíso","institutionCode":"CM015","publicationDate":"2021/07/29","year":2019,"monthString":"Noviembre","contractType":"Docente","name":"ANDREA CAROLINA","surname1":"GUTIERREZ","surname2":"VALENZUELA","salaryGrade":"No Asimilado a Grado","qualificationType":"SIN TITULO","position":"PROFESOR BASICO COMUN","region":"Región de Valparaíso","extraBenefits":"(95)(107)(122)(73)(15)(87)","currency":"Pesos","salaryBeforeTaxes":1038558,"salaryAfterTaxes":592847,"bonusDayTime":"","extraHoursDayTime":"","bonusNightTime":"","extraHoursNightTime":"","bonusHolidays":"","extraHoursHolidays":"","startDate":"20/03/2014","endDate":"29/02/2020","obs":"D314","link":"No","travelExpenses":"","activated":"SÍ","fullName":"ANDREA CAROLINA GUTIERREZ VALENZUELA","slug":"andrea_carolina_gutierrez_valenzuela","month":11,"cleanFullName":"andrea carolina gutierrez valenzuela"},"12":{"internalPath":"/Area de Educación/Año 2019/Diciembre","institution":"Corporación Municipal de Valparaíso","institutionCode":"CM015","publicationDate":"2021/07/29","year":2019,"monthString":"Diciembre","contractType":"Docente","name":"ANDREA CAROLINA","surname1":"GUTIERREZ","surname2":"VALENZUELA","salaryGrade":"No Asimilado a Grado","qualificationType":"SIN TITULO","position":"PROFESOR BASICO COMUN","region":"Región de Valparaíso","extraBenefits":"(87)(15)(73)(122)(107)(95)","currency":"Pesos","salaryBeforeTaxes":1057340,"salaryAfterTaxes":607927,"bonusDayTime":"","extraHoursDayTime":"","bonusNightTime":0,"extraHoursNightTime":0,"bonusHolidays":0,"extraHoursHolidays":0,"startDate":"20/03/2014","endDate":"29/02/2020","obs":"D314","link":"No","travelExpenses":"","activated":"SÍ","fullName":"ANDREA CAROLINA GUTIERREZ VALENZUELA","slug":"andrea_carolina_gutierrez_valenzuela","month":12,"cleanFullName":"andrea carolina gutierrez valenzuela"}},"2020":{"1":{"internalPath":"/Area de Educación/Año 2020/Enero","institution":"Corporación Municipal de Valparaíso","institutionCode":"CM015","publicationDate":"2021/07/29","year":2020,"monthString":"Enero","contractType":"Docente","name":"ANDREA CAROLINA","surname1":"GUTIERREZ","surname2":"VALENZUELA","salaryGrade":"No Asimilado a Grado","qualificationType":"SIN TITULO","position":"PROFESOR BASICO COMUN","region":"Región de Valparaíso","extraBenefits":"(95)(107)(122)(73)(15)(87)","currency":"Pesos","salaryBeforeTaxes":1066966,"salaryAfterTaxes":615552,"bonusDayTime":"","extraHoursDayTime":"","bonusNightTime":0,"extraHoursNightTime":0,"bonusHolidays":0,"extraHoursHolidays":0,"startDate":"20/03/2014","endDate":"29/02/2020","obs":"D314","link":"No","travelExpenses":"","activated":"SÍ","fullName":"ANDREA CAROLINA GUTIERREZ VALENZUELA","slug":"andrea_carolina_gutierrez_valenzuela","month":1,"cleanFullName":"andrea carolina gutierrez valenzuela"},"2":{"internalPath":"/Area de Educación/Año 2020/Febrero","institution":"Corporación Municipal de Valparaíso","institutionCode":"CM015","publicationDate":"2021/07/29","year":2020,"monthString":"Febrero","contractType":"Docente","name":"ANDREA CAROLINA","surname1":"GUTIERREZ","surname2":"VALENZUELA","salaryGrade":"No Asimilado a Grado","qualificationType":"SIN TITULO","position":"PROFESOR BASICO COMUN","region":"Región de Valparaíso","extraBenefits":"(87)(15)(73)(122)(107)(95)","currency":"Pesos","salaryBeforeTaxes":1066966,"salaryAfterTaxes":614979,"bonusDayTime":0,"extraHoursDayTime":0,"bonusNightTime":0,"extraHoursNightTime":0,"bonusHolidays":0,"extraHoursHolidays":0,"startDate":"20/03/2014","endDate":"29/02/2020","obs":"D314","link":"No","travelExpenses":"","activated":"SÍ","fullName":"ANDREA CAROLINA GUTIERREZ VALENZUELA","slug":"andrea_carolina_gutierrez_valenzuela","month":2,"cleanFullName":"andrea carolina gutierrez valenzuela"}}}}