{"leonardo_ariel_muñoz_vergara":{"2017":{"11":{"internalPath":"/2017/Noviembre","institution":"SEREMI de Salud del Bío Bío","institutionCode":"AO048","publicationDate":"2021/07/13","year":2017,"monthString":"Noviembre","contractType":"Profesional","name":"LEONARDO ARIEL","surname1":"MUÑOZ","surname2":"VERGARA","salaryGrade":11,"qualificationType":"ING. INFORMATICA","position":"JEFE DEPARTAMENTO TIC","region":"Región del Biobío","extraBenefits":"(33)(33)","currency":"Pesos","salaryBeforeTaxes":1731480,"salaryAfterTaxes":1404690,"bonusDayTime":"","extraHoursDayTime":"","bonusNightTime":"","extraHoursNightTime":"","bonusHolidays":"","extraHoursHolidays":"","startDate":"01/01/2017","endDate":"31/12/2017","obs":"Sin observaciones","link":"No","travelExpenses":"","activated":"SÍ","fullName":"LEONARDO ARIEL MUÑOZ VERGARA","slug":"leonardo_ariel_muñoz_vergara","month":11},"12":{"internalPath":"/2017/Diciembre","institution":"SEREMI de Salud del Bío Bío","institutionCode":"AO048","publicationDate":"2021/07/13","year":2017,"monthString":"Diciembre","contractType":"Profesional","name":"LEONARDO ARIEL","surname1":"MUÑOZ","surname2":"VERGARA","salaryGrade":11,"qualificationType":"ING. INFORMATICA","position":"JEFE DEPARTAMENTO TIC","region":"Región del Biobío","extraBenefits":"(37)(33)","currency":"Pesos","salaryBeforeTaxes":2057527,"salaryAfterTaxes":1557453,"bonusDayTime":"","extraHoursDayTime":"","bonusNightTime":"","extraHoursNightTime":"","bonusHolidays":"","extraHoursHolidays":"","startDate":"01/01/2017","endDate":"31/12/2017","obs":"Sin observaciones","link":"No","travelExpenses":"","activated":"SÍ","fullName":"LEONARDO ARIEL MUÑOZ VERGARA","slug":"leonardo_ariel_muñoz_vergara","month":12}},"2018":{"1":{"internalPath":"/2018/Enero","institution":"SEREMI de Salud del Bío Bío","institutionCode":"AO048","publicationDate":"2021/07/13","year":2018,"monthString":"Enero","contractType":"Profesional","name":"LEONARDO ARIEL","surname1":"MUÑOZ","surname2":"VERGARA","salaryGrade":11,"qualificationType":"ING. INFORMATICA","position":"JEFE DEPARTAMENTO TIC","region":"Región del Biobío","extraBenefits":"(186)(37)","currency":"Pesos","salaryBeforeTaxes":1859897,"salaryAfterTaxes":1522750,"bonusDayTime":"","extraHoursDayTime":"","bonusNightTime":"","extraHoursNightTime":"","bonusHolidays":"","extraHoursHolidays":"","startDate":"01/01/2018","endDate":"31/12/2018","obs":"Sin observaciones","link":"No","travelExpenses":"","activated":"SÍ","fullName":"LEONARDO ARIEL MUÑOZ VERGARA","slug":"leonardo_ariel_muñoz_vergara","month":1},"2":{"internalPath":"/2018/Febrero","institution":"SEREMI de Salud del Bío Bío","institutionCode":"AO048","publicationDate":"2021/07/13","year":2018,"monthString":"Febrero","contractType":"Profesional","name":"LEONARDO ARIEL","surname1":"MUÑOZ","surname2":"VERGARA","salaryGrade":11,"qualificationType":"ING. INFORMATICA","position":"JEFE DEPARTAMENTO TIC","region":"Región del Biobío","extraBenefits":"(37)(186)","currency":"Pesos","salaryBeforeTaxes":1782815,"salaryAfterTaxes":1445693,"bonusDayTime":"","extraHoursDayTime":"","bonusNightTime":"","extraHoursNightTime":"","bonusHolidays":"","extraHoursHolidays":"","startDate":"01/01/2018","endDate":"31/12/2018","obs":"Sin observaciones","link":"No","travelExpenses":"","activated":"SÍ","fullName":"LEONARDO ARIEL MUÑOZ VERGARA","slug":"leonardo_ariel_muñoz_vergara","month":2},"3":{"internalPath":"/2018/Marzo","institution":"SEREMI de Salud del Bío Bío","institutionCode":"AO048","publicationDate":"2021/07/13","year":2018,"monthString":"Marzo","contractType":"Profesional","name":"LEONARDO ARIEL","surname1":"MUÑOZ","surname2":"VERGARA","salaryGrade":11,"qualificationType":"ING. INFORMATICA","position":"JEFE DEPARTAMENTO TIC","region":"Región del Biobío","extraBenefits":"(186)(37)","currency":"Pesos","salaryBeforeTaxes":1975027,"salaryAfterTaxes":1445820,"bonusDayTime":"","extraHoursDayTime":"","bonusNightTime":"","extraHoursNightTime":"","bonusHolidays":"","extraHoursHolidays":"","startDate":"01/01/2018","endDate":"31/12/2018","obs":"Sin observaciones","link":"No","travelExpenses":"","activated":"SÍ","fullName":"LEONARDO ARIEL MUÑOZ VERGARA","slug":"leonardo_ariel_muñoz_vergara","month":3},"4":{"internalPath":"/2018/Abril","institution":"SEREMI de Salud del Bío Bío","institutionCode":"AO048","publicationDate":"2021/07/13","year":2018,"monthString":"Abril","contractType":"Profesional","name":"LEONARDO ARIEL","surname1":"MUÑOZ","surname2":"VERGARA","salaryGrade":11,"qualificationType":"ING. INFORMATICA","position":"JEFE DEPARTAMENTO TIC","region":"Región del Biobío","extraBenefits":"(37)(186)","currency":"Pesos","salaryBeforeTaxes":1782815,"salaryAfterTaxes":1445820,"bonusDayTime":"","extraHoursDayTime":"","bonusNightTime":"","extraHoursNightTime":"","bonusHolidays":"","extraHoursHolidays":"","startDate":"01/01/2018","endDate":"31/12/2018","obs":"Sin observaciones","link":"No","travelExpenses":"","activated":"SÍ","fullName":"LEONARDO ARIEL MUÑOZ VERGARA","slug":"leonardo_ariel_muñoz_vergara","month":4},"5":{"internalPath":"/2018/Mayo","institution":"SEREMI de Salud del Bío Bío","institutionCode":"AO048","publicationDate":"2021/07/13","year":2018,"monthString":"Mayo","contractType":"Profesional","name":"LEONARDO ARIEL","surname1":"MUÑOZ","surname2":"VERGARA","salaryGrade":11,"qualificationType":"ING. INFORMATICA","position":"JEFE DEPARTAMENTO TIC","region":"Región del Biobío","extraBenefits":"(37)(186)","currency":"Pesos","salaryBeforeTaxes":1782815,"salaryAfterTaxes":1445871,"bonusDayTime":"","extraHoursDayTime":"","bonusNightTime":"","extraHoursNightTime":"","bonusHolidays":"","extraHoursHolidays":"","startDate":"01/01/2018","endDate":"31/12/2018","obs":"Sin observaciones","link":"No","travelExpenses":"","activated":"SÍ","fullName":"LEONARDO ARIEL MUÑOZ VERGARA","slug":"leonardo_ariel_muñoz_vergara","month":5},"6":{"internalPath":"/2018/Junio","institution":"SEREMI de Salud del Bío Bío","institutionCode":"AO048","publicationDate":"2021/07/13","year":2018,"monthString":"Junio","contractType":"Profesional","name":"LEONARDO ARIEL","surname1":"MUÑOZ","surname2":"VERGARA","salaryGrade":11,"qualificationType":"ING. INFORMATICA","position":"JEFE DEPARTAMENTO TIC","region":"Región del Biobío","extraBenefits":"(186)(37)","currency":"Pesos","salaryBeforeTaxes":1975027,"salaryAfterTaxes":1445948,"bonusDayTime":"","extraHoursDayTime":"","bonusNightTime":"","extraHoursNightTime":"","bonusHolidays":"","extraHoursHolidays":"","startDate":"01/01/2018","endDate":"31/12/2018","obs":"Sin observaciones","link":"No","travelExpenses":"","activated":"SÍ","fullName":"LEONARDO ARIEL MUÑOZ VERGARA","slug":"leonardo_ariel_muñoz_vergara","month":6},"7":{"internalPath":"/2018/Julio","institution":"SEREMI de Salud del Bío Bío","institutionCode":"AO048","publicationDate":"2021/07/13","year":2018,"monthString":"Julio","contractType":"Profesional","name":"LEONARDO ARIEL","surname1":"MUÑOZ","surname2":"VERGARA","salaryGrade":11,"qualificationType":"ING. INFORMATICA","position":"JEFE DEPARTAMENTO TIC","region":"Región del Biobío","extraBenefits":"(37)(186)","currency":"Pesos","salaryBeforeTaxes":1782815,"salaryAfterTaxes":1446025,"bonusDayTime":"","extraHoursDayTime":"","bonusNightTime":"","extraHoursNightTime":"","bonusHolidays":"","extraHoursHolidays":"","startDate":"01/01/2018","endDate":"31/12/2018","obs":"Sin observaciones","link":"No","travelExpenses":"","activated":"SÍ","fullName":"LEONARDO ARIEL MUÑOZ VERGARA","slug":"leonardo_ariel_muñoz_vergara","month":7},"8":{"internalPath":"/2018/Agosto","institution":"SEREMI de Salud del Bío Bío","institutionCode":"AO048","publicationDate":"2021/07/13","year":2018,"monthString":"Agosto","contractType":"Profesional","name":"LEONARDO ARIEL","surname1":"MUÑOZ","surname2":"VERGARA","salaryGrade":11,"qualificationType":"ING. INFORMATICA","position":"JEFE DEPARTAMENTO TIC","region":"Región del Biobío","extraBenefits":"(186)(37)","currency":"Pesos","salaryBeforeTaxes":1782815,"salaryAfterTaxes":1446051,"bonusDayTime":"","extraHoursDayTime":"","bonusNightTime":"","extraHoursNightTime":"","bonusHolidays":"","extraHoursHolidays":"","startDate":"01/01/2018","endDate":"31/12/2018","obs":"Sin observaciones","link":"No","travelExpenses":"","activated":"SÍ","fullName":"LEONARDO ARIEL MUÑOZ VERGARA","slug":"leonardo_ariel_muñoz_vergara","month":8},"9":{"internalPath":"/2018/Septiembre","institution":"SEREMI de Salud del Bío Bío","institutionCode":"AO048","publicationDate":"2021/07/13","year":2018,"monthString":"Septiembre","contractType":"Profesional","name":"LEONARDO ARIEL","surname1":"MUÑOZ","surname2":"VERGARA","salaryGrade":11,"qualificationType":"ING. INFORMATICA","position":"JEFE DEPARTAMENTO TIC","region":"Región del Biobío","extraBenefits":"(37)(186)","currency":"Pesos","salaryBeforeTaxes":1975027,"salaryAfterTaxes":1494770,"bonusDayTime":"","extraHoursDayTime":"","bonusNightTime":"","extraHoursNightTime":"","bonusHolidays":"","extraHoursHolidays":"","startDate":"01/01/2018","endDate":"31/12/2018","obs":"Sin observaciones","link":"No","travelExpenses":"","activated":"SÍ","fullName":"LEONARDO ARIEL MUÑOZ VERGARA","slug":"leonardo_ariel_muñoz_vergara","month":9},"10":{"internalPath":"/2018/Octubre","institution":"SEREMI de Salud del Bío Bío","institutionCode":"AO048","publicationDate":"2021/07/13","year":2018,"monthString":"Octubre","contractType":"Profesional","name":"LEONARDO ARIEL","surname1":"MUÑOZ","surname2":"VERGARA","salaryGrade":11,"qualificationType":"ING. INFORMATICA","position":"JEFE DEPARTAMENTO TIC","region":"Región del Biobío","extraBenefits":"(186)(37)","currency":"Pesos","salaryBeforeTaxes":1782815,"salaryAfterTaxes":1446206,"bonusDayTime":"","extraHoursDayTime":"","bonusNightTime":"","extraHoursNightTime":"","bonusHolidays":"","extraHoursHolidays":"","startDate":"01/01/2018","endDate":"31/12/2018","obs":"Sin observaciones","link":"No","travelExpenses":"","activated":"SÍ","fullName":"LEONARDO ARIEL MUÑOZ VERGARA","slug":"leonardo_ariel_muñoz_vergara","month":10},"11":{"internalPath":"/2018/Noviembre","institution":"SEREMI de Salud del Bío Bío","institutionCode":"AO048","publicationDate":"2021/07/13","year":2018,"monthString":"Noviembre","contractType":"Profesional","name":"LEONARDO ARIEL","surname1":"MUÑOZ","surname2":"VERGARA","salaryGrade":11,"qualificationType":"ING. INFORMATICA","position":"JEFE DEPARTAMENTO TIC","region":"Región del Biobío","extraBenefits":"(37)(186)","currency":"Pesos","salaryBeforeTaxes":1782815,"salaryAfterTaxes":1446284,"bonusDayTime":"","extraHoursDayTime":"","bonusNightTime":"","extraHoursNightTime":"","bonusHolidays":"","extraHoursHolidays":"","startDate":"01/01/2018","endDate":"31/12/2018","obs":"Sin observaciones","link":"No","travelExpenses":"","activated":"SÍ","fullName":"LEONARDO ARIEL MUÑOZ VERGARA","slug":"leonardo_ariel_muñoz_vergara","month":11},"12":{"internalPath":"/2018/Diciembre","institution":"SEREMI de Salud del Bío Bío","institutionCode":"AO048","publicationDate":"2021/07/13","year":2018,"monthString":"Diciembre","contractType":"Profesional","name":"LEONARDO ARIEL","surname1":"MUÑOZ","surname2":"VERGARA","salaryGrade":11,"qualificationType":"ING. INFORMATICA","position":"JEFE DEPARTAMENTO TIC","region":"Región del Biobío","extraBenefits":"(186)(37)","currency":"Pesos","salaryBeforeTaxes":2135654,"salaryAfterTaxes":1888357,"bonusDayTime":"","extraHoursDayTime":"","bonusNightTime":"","extraHoursNightTime":"","bonusHolidays":"","extraHoursHolidays":"","startDate":"01/01/2018","endDate":"31/12/2018","obs":"Sin observaciones","link":"No","travelExpenses":"","activated":"SÍ","fullName":"LEONARDO ARIEL MUÑOZ VERGARA","slug":"leonardo_ariel_muñoz_vergara","month":12}},"2019":{"1":{"internalPath":"/2019/Enero","institution":"SEREMI de Salud del Bío Bío","institutionCode":"AO048","publicationDate":"2021/07/13","year":2019,"monthString":"Enero","contractType":"Profesional","name":"LEONARDO ARIEL","surname1":"MUÑOZ","surname2":"VERGARA","salaryGrade":11,"qualificationType":"ING. INFORMATICA","position":"JEFE DEPARTAMENTO TIC","region":"Región del Biobío","extraBenefits":"(37)(186)","currency":"Pesos","salaryBeforeTaxes":1928215,"salaryAfterTaxes":1579100,"bonusDayTime":"","extraHoursDayTime":"","bonusNightTime":"","extraHoursNightTime":"","bonusHolidays":"","extraHoursHolidays":"","startDate":"01/01/2019","endDate":"31/12/2019","obs":"Sin observaciones","link":"No","travelExpenses":"","activated":"SÍ","fullName":"LEONARDO ARIEL MUÑOZ VERGARA","slug":"leonardo_ariel_muñoz_vergara","month":1},"2":{"internalPath":"/2019/Febrero","institution":"SEREMI de Salud del Bío Bío","institutionCode":"AO048","publicationDate":"2021/07/13","year":2019,"monthString":"Febrero","contractType":"Profesional","name":"LEONARDO ARIEL","surname1":"MUÑOZ","surname2":"VERGARA","salaryGrade":11,"qualificationType":"ING. INFORMATICA","position":"JEFE DEPARTAMENTO TIC","region":"Región del Biobío","extraBenefits":"(186)(37)","currency":"Pesos","salaryBeforeTaxes":1845215,"salaryAfterTaxes":1496074,"bonusDayTime":"","extraHoursDayTime":"","bonusNightTime":"","extraHoursNightTime":"","bonusHolidays":"","extraHoursHolidays":"","startDate":"01/01/2019","endDate":"31/12/2019","obs":"Sin observaciones","link":"No","travelExpenses":"","activated":"SÍ","fullName":"LEONARDO ARIEL MUÑOZ VERGARA","slug":"leonardo_ariel_muñoz_vergara","month":2},"3":{"internalPath":"/2019/Marzo","institution":"SEREMI de Salud del Bío Bío","institutionCode":"AO048","publicationDate":"2021/07/13","year":2019,"monthString":"Marzo","contractType":"Profesional","name":"LEONARDO ARIEL","surname1":"MUÑOZ","surname2":"VERGARA","salaryGrade":11,"qualificationType":"ING. INFORMATICA","position":"JEFE DEPARTAMENTO TIC","region":"Región del Biobío","extraBenefits":"(37)(186)","currency":"Pesos","salaryBeforeTaxes":2044154,"salaryAfterTaxes":1646739,"bonusDayTime":"","extraHoursDayTime":"","bonusNightTime":"","extraHoursNightTime":"","bonusHolidays":"","extraHoursHolidays":"","startDate":"01/01/2019","endDate":"31/12/2019","obs":"Sin observaciones","link":"No","travelExpenses":"","activated":"SÍ","fullName":"LEONARDO ARIEL MUÑOZ VERGARA","slug":"leonardo_ariel_muñoz_vergara","month":3},"4":{"internalPath":"/2019/Abril","institution":"SEREMI de Salud del Bío Bío","institutionCode":"AO048","publicationDate":"2021/07/13","year":2019,"monthString":"Abril","contractType":"Profesional","name":"LEONARDO ARIEL","surname1":"MUÑOZ","surname2":"VERGARA","salaryGrade":11,"qualificationType":"ING. INFORMATICA","position":"JEFE DEPARTAMENTO TIC","region":"Región del Biobío","extraBenefits":"(186)(37)","currency":"Pesos","salaryBeforeTaxes":1845215,"salaryAfterTaxes":1496100,"bonusDayTime":"","extraHoursDayTime":"","bonusNightTime":"","extraHoursNightTime":"","bonusHolidays":"","extraHoursHolidays":"","startDate":"01/01/2019","endDate":"31/12/2019","obs":"Sin observaciones","link":"No","travelExpenses":"","activated":"SÍ","fullName":"LEONARDO ARIEL MUÑOZ VERGARA","slug":"leonardo_ariel_muñoz_vergara","month":4},"5":{"internalPath":"/2019/Mayo","institution":"SEREMI de Salud del Bío Bío","institutionCode":"AO048","publicationDate":"2021/07/13","year":2019,"monthString":"Mayo","contractType":"Profesional","name":"LEONARDO ARIEL","surname1":"MUÑOZ","surname2":"VERGARA","salaryGrade":11,"qualificationType":"ING. INFORMATICA","position":"JEFE DEPARTAMENTO TIC","region":"Región del Biobío","extraBenefits":"(37)(186)","currency":"Pesos","salaryBeforeTaxes":1845215,"salaryAfterTaxes":1496231,"bonusDayTime":"","extraHoursDayTime":"","bonusNightTime":"","extraHoursNightTime":"","bonusHolidays":"","extraHoursHolidays":"","startDate":"01/01/2019","endDate":"31/12/2019","obs":"Sin observaciones","link":"No","travelExpenses":"","activated":"SÍ","fullName":"LEONARDO ARIEL MUÑOZ VERGARA","slug":"leonardo_ariel_muñoz_vergara","month":5},"6":{"internalPath":"/2019/Junio","institution":"SEREMI de Salud del Bío Bío","institutionCode":"AO048","publicationDate":"2021/07/13","year":2019,"monthString":"Junio","contractType":"Profesional","name":"LEONARDO ARIEL","surname1":"MUÑOZ","surname2":"VERGARA","salaryGrade":11,"qualificationType":"ING. INFORMATICA","position":"JEFE DEPARTAMENTO TIC","region":"Región del Biobío","extraBenefits":"(186)(37)","currency":"Pesos","salaryBeforeTaxes":2044154,"salaryAfterTaxes":1496310,"bonusDayTime":"","extraHoursDayTime":"","bonusNightTime":"","extraHoursNightTime":"","bonusHolidays":"","extraHoursHolidays":"","startDate":"01/01/2019","endDate":"31/12/2019","obs":"Sin observaciones","link":"No","travelExpenses":"","activated":"SÍ","fullName":"LEONARDO ARIEL MUÑOZ VERGARA","slug":"leonardo_ariel_muñoz_vergara","month":6},"7":{"internalPath":"/2019/Julio","institution":"SEREMI de Salud del Bío Bío","institutionCode":"AO048","publicationDate":"2021/07/13","year":2019,"monthString":"Julio","contractType":"Profesional","name":"LEONARDO ARIEL","surname1":"MUÑOZ","surname2":"VERGARA","salaryGrade":11,"qualificationType":"ING. INFORMATICA","position":"JEFE DEPARTAMENTO TIC","region":"Región del Biobío","extraBenefits":"(37)(186)","currency":"Pesos","salaryBeforeTaxes":1845215,"salaryAfterTaxes":1476151,"bonusDayTime":"","extraHoursDayTime":"","bonusNightTime":"","extraHoursNightTime":"","bonusHolidays":"","extraHoursHolidays":"","startDate":"01/01/2019","endDate":"31/12/2019","obs":"Sin observaciones","link":"No","travelExpenses":"","activated":"SÍ","fullName":"LEONARDO ARIEL MUÑOZ VERGARA","slug":"leonardo_ariel_muñoz_vergara","month":7},"8":{"internalPath":"/2019/Agosto","institution":"SEREMI de Salud del Bío Bío","institutionCode":"AO048","publicationDate":"2021/07/13","year":2019,"monthString":"Agosto","contractType":"Profesional","name":"LEONARDO ARIEL","surname1":"MUÑOZ","surname2":"VERGARA","salaryGrade":11,"qualificationType":"ING. INFORMATICA","position":"JEFE DEPARTAMENTO TIC","region":"Región del Biobío","extraBenefits":"(186)(37)","currency":"Pesos","salaryBeforeTaxes":1845215,"salaryAfterTaxes":1476151,"bonusDayTime":"","extraHoursDayTime":"","bonusNightTime":"","extraHoursNightTime":"","bonusHolidays":"","extraHoursHolidays":"","startDate":"01/01/2019","endDate":"31/12/2019","obs":"Sin observaciones","link":"No","travelExpenses":"","activated":"SÍ","fullName":"LEONARDO ARIEL MUÑOZ VERGARA","slug":"leonardo_ariel_muñoz_vergara","month":8},"9":{"internalPath":"/2019/Septiembre","institution":"SEREMI de Salud del Bío Bío","institutionCode":"AO048","publicationDate":"2021/07/13","year":2019,"monthString":"Septiembre","contractType":"Profesional","name":"LEONARDO ARIEL","surname1":"MUÑOZ","surname2":"VERGARA","salaryGrade":11,"qualificationType":"ING. INFORMATICA","position":"JEFE DEPARTAMENTO TIC","region":"Región del Biobío","extraBenefits":"(37)(186)","currency":"Pesos","salaryBeforeTaxes":2044154,"salaryAfterTaxes":1526522,"bonusDayTime":"","extraHoursDayTime":"","bonusNightTime":"","extraHoursNightTime":"","bonusHolidays":"","extraHoursHolidays":"","startDate":"01/01/2019","endDate":"31/12/2019","obs":"Sin observaciones","link":"No","travelExpenses":"","activated":"SÍ","fullName":"LEONARDO ARIEL MUÑOZ VERGARA","slug":"leonardo_ariel_muñoz_vergara","month":9},"10":{"internalPath":"/2019/Octubre","institution":"SEREMI de Salud del Bío Bío","institutionCode":"AO048","publicationDate":"2021/07/13","year":2019,"monthString":"Octubre","contractType":"Profesional","name":"LEONARDO ARIEL","surname1":"MUÑOZ","surname2":"VERGARA","salaryGrade":11,"qualificationType":"ING. INFORMATICA","position":"JEFE DEPARTAMENTO TIC","region":"Región del Biobío","extraBenefits":"(186)(37)","currency":"Pesos","salaryBeforeTaxes":1845215,"salaryAfterTaxes":1476257,"bonusDayTime":"","extraHoursDayTime":"","bonusNightTime":"","extraHoursNightTime":"","bonusHolidays":"","extraHoursHolidays":"","startDate":"01/01/2019","endDate":"31/12/2019","obs":"Sin observaciones","link":"No","travelExpenses":"","activated":"SÍ","fullName":"LEONARDO ARIEL MUÑOZ VERGARA","slug":"leonardo_ariel_muñoz_vergara","month":10},"11":{"internalPath":"/2019/Noviembre","institution":"SEREMI de Salud del Bío Bío","institutionCode":"AO048","publicationDate":"2021/07/13","year":2019,"monthString":"Noviembre","contractType":"Profesional","name":"LEONARDO ARIEL","surname1":"MUÑOZ","surname2":"VERGARA","salaryGrade":11,"qualificationType":"ING. INFORMATICA","position":"JEFE DEPARTAMENTO TIC","region":"Región del Biobío","extraBenefits":"(37)(186)","currency":"Pesos","salaryBeforeTaxes":1845215,"salaryAfterTaxes":1476257,"bonusDayTime":"","extraHoursDayTime":"","bonusNightTime":"","extraHoursNightTime":"","bonusHolidays":"","extraHoursHolidays":"","startDate":"01/01/2019","endDate":"31/12/2019","obs":"Sin observaciones","link":"No","travelExpenses":"","activated":"SÍ","fullName":"LEONARDO ARIEL MUÑOZ VERGARA","slug":"leonardo_ariel_muñoz_vergara","month":11},"12":{"internalPath":"/2019/Diciembre","institution":"SEREMI de Salud del Bío Bío","institutionCode":"AO048","publicationDate":"2021/07/13","year":2019,"monthString":"Diciembre","contractType":"Profesional","name":"LEONARDO ARIEL","surname1":"MUÑOZ","surname2":"VERGARA","salaryGrade":11,"qualificationType":"ING. INFORMATICA","position":"JEFE DEPARTAMENTO TIC","region":"Región del Biobío","extraBenefits":"(186)(37)","currency":"Pesos","salaryBeforeTaxes":2138216,"salaryAfterTaxes":1625959,"bonusDayTime":"","extraHoursDayTime":"","bonusNightTime":"","extraHoursNightTime":"","bonusHolidays":"","extraHoursHolidays":"","startDate":"01/01/2019","endDate":"31/12/2019","obs":"Sin observaciones","link":"No","travelExpenses":"","activated":"SÍ","fullName":"LEONARDO ARIEL MUÑOZ VERGARA","slug":"leonardo_ariel_muñoz_vergara","month":12}},"2020":{"1":{"internalPath":"/2020/Enero","institution":"SEREMI de Salud del Bío Bío","institutionCode":"AO048","publicationDate":"2021/07/13","year":2020,"monthString":"Enero","contractType":"Profesional","name":"LEONARDO ARIEL","surname1":"MUÑOZ","surname2":"VERGARA","salaryGrade":11,"qualificationType":"ING. INFORMATICA","position":"JEFE DEPARTAMENTO TIC","region":"Región del Biobío","extraBenefits":"(37)(186)","currency":"Pesos","salaryBeforeTaxes":1982203,"salaryAfterTaxes":1517084,"bonusDayTime":"","extraHoursDayTime":"","bonusNightTime":"","extraHoursNightTime":"","bonusHolidays":"","extraHoursHolidays":"","startDate":"01/01/2020","endDate":"31/12/2020","obs":"Sin observaciones","link":"No","travelExpenses":"","activated":"SÍ","fullName":"LEONARDO ARIEL MUÑOZ VERGARA","slug":"leonardo_ariel_muñoz_vergara","month":1},"2":{"internalPath":"/2020/Febrero","institution":"SEREMI de Salud del Bío Bío","institutionCode":"AO048","publicationDate":"2021/07/13","year":2020,"monthString":"Febrero","contractType":"Profesional","name":"LEONARDO ARIEL","surname1":"MUÑOZ","surname2":"VERGARA","salaryGrade":11,"qualificationType":"ING. INFORMATICA","position":"JEFE DEPARTAMENTO TIC","region":"Región del Biobío","extraBenefits":"(37)(186)","currency":"Pesos","salaryBeforeTaxes":1895394,"salaryAfterTaxes":1515965,"bonusDayTime":"","extraHoursDayTime":"","bonusNightTime":"","extraHoursNightTime":"","bonusHolidays":"","extraHoursHolidays":"","startDate":"01/01/2020","endDate":"31/12/2020","obs":"Sin observaciones","link":"No","travelExpenses":"","activated":"SÍ","fullName":"LEONARDO ARIEL MUÑOZ VERGARA","slug":"leonardo_ariel_muñoz_vergara","month":2},"3":{"internalPath":"/2020/Marzo","institution":"SEREMI de Salud del Bío Bío","institutionCode":"AO048","publicationDate":"2021/07/13","year":2020,"monthString":"Marzo","contractType":"Profesional","name":"LEONARDO ARIEL","surname1":"MUÑOZ","surname2":"VERGARA","salaryGrade":11,"qualificationType":"ING. INFORMATICA","position":"JEFE DEPARTAMENTO TIC","region":"Región del Biobío","extraBenefits":"(186)(37)","currency":"Pesos","salaryBeforeTaxes":2101388,"salaryAfterTaxes":1517272,"bonusDayTime":"","extraHoursDayTime":"","bonusNightTime":"","extraHoursNightTime":"","bonusHolidays":"","extraHoursHolidays":"","startDate":"01/01/2020","endDate":"31/12/2020","obs":"Sin observaciones","link":"No","travelExpenses":"","activated":"SÍ","fullName":"LEONARDO ARIEL MUÑOZ VERGARA","slug":"leonardo_ariel_muñoz_vergara","month":3},"4":{"internalPath":"/2020/Abril","institution":"SEREMI de Salud del Bío Bío","institutionCode":"AO048","publicationDate":"2021/07/13","year":2020,"monthString":"Abril","contractType":"Profesional","name":"LEONARDO ARIEL","surname1":"MUÑOZ","surname2":"VERGARA","salaryGrade":11,"qualificationType":"ING. INFORMATICA","position":"JEFE DEPARTAMENTO TIC","region":"Región del Biobío","extraBenefits":"(186)(37)","currency":"Pesos","salaryBeforeTaxes":1896879,"salaryAfterTaxes":1517380,"bonusDayTime":"","extraHoursDayTime":"","bonusNightTime":"","extraHoursNightTime":"","bonusHolidays":"","extraHoursHolidays":"","startDate":"01/01/2020","endDate":"31/12/2020","obs":"Sin observaciones","link":"No","travelExpenses":"","activated":"SÍ","fullName":"LEONARDO ARIEL MUÑOZ VERGARA","slug":"leonardo_ariel_muñoz_vergara","month":4},"5":{"internalPath":"/2020/Mayo","institution":"SEREMI de Salud del Bío Bío","institutionCode":"AO048","publicationDate":"2021/07/13","year":2020,"monthString":"Mayo","contractType":"Profesional","name":"LEONARDO ARIEL","surname1":"MUÑOZ","surname2":"VERGARA","salaryGrade":11,"qualificationType":"ING. INFORMATICA","position":"JEFE DEPARTAMENTO TIC","region":"Región del Biobío","extraBenefits":"(186)(37)","currency":"Pesos","salaryBeforeTaxes":1922256,"salaryAfterTaxes":1541824,"bonusDayTime":"","extraHoursDayTime":"","bonusNightTime":"","extraHoursNightTime":"","bonusHolidays":"","extraHoursHolidays":"","startDate":"01/01/2020","endDate":"31/12/2020","obs":"Sin observaciones","link":"No","travelExpenses":"","activated":"SÍ","fullName":"LEONARDO ARIEL MUÑOZ VERGARA","slug":"leonardo_ariel_muñoz_vergara","month":5},"6":{"internalPath":"/2020/Junio","institution":"SEREMI de Salud del Bío Bío","institutionCode":"AO048","publicationDate":"2021/07/13","year":2020,"monthString":"Junio","contractType":"Profesional","name":"LEONARDO ARIEL","surname1":"MUÑOZ","surname2":"VERGARA","salaryGrade":11,"qualificationType":"ING. INFORMATICA","position":"JEFE DEPARTAMENTO TIC","region":"Región del Biobío","extraBenefits":"(186)(37)","currency":"Pesos","salaryBeforeTaxes":2135224,"salaryAfterTaxes":1549944,"bonusDayTime":"","extraHoursDayTime":"","bonusNightTime":"","extraHoursNightTime":"","bonusHolidays":"","extraHoursHolidays":"","startDate":"01/01/2020","endDate":"31/12/2020","obs":"Sin observaciones","link":"No","travelExpenses":"","activated":"SÍ","fullName":"LEONARDO ARIEL MUÑOZ VERGARA","slug":"leonardo_ariel_muñoz_vergara","month":6},"7":{"internalPath":"/2020/Julio","institution":"SEREMI de Salud del Bío Bío","institutionCode":"AO048","publicationDate":"2021/07/13","year":2020,"monthString":"Julio","contractType":"Profesional","name":"LEONARDO ARIEL","surname1":"MUÑOZ","surname2":"VERGARA","salaryGrade":11,"qualificationType":"ING. INFORMATICA","position":"JEFE DEPARTAMENTO TIC","region":"Región del Biobío","extraBenefits":"(186)(37)","currency":"Pesos","salaryBeforeTaxes":1947737,"salaryAfterTaxes":1564536,"bonusDayTime":"","extraHoursDayTime":"","bonusNightTime":"","extraHoursNightTime":"","bonusHolidays":"","extraHoursHolidays":"","startDate":"01/01/2020","endDate":"31/12/2020","obs":"Sin observaciones","link":"No","travelExpenses":"","activated":"SÍ","fullName":"LEONARDO ARIEL MUÑOZ VERGARA","slug":"leonardo_ariel_muñoz_vergara","month":7},"8":{"internalPath":"/2020/Agosto","institution":"SEREMI de Salud del Bío Bío","institutionCode":"AO048","publicationDate":"2021/07/13","year":2020,"monthString":"Agosto","contractType":"Profesional","name":"LEONARDO ARIEL","surname1":"MUÑOZ","surname2":"VERGARA","salaryGrade":11,"qualificationType":"ING. INFORMATICA","position":"JEFE DEPARTAMENTO TIC","region":"Región del Biobío","extraBenefits":"(186)(37)","currency":"Pesos","salaryBeforeTaxes":1905442,"salaryAfterTaxes":1524037,"bonusDayTime":"","extraHoursDayTime":"","bonusNightTime":"","extraHoursNightTime":"","bonusHolidays":"","extraHoursHolidays":"","startDate":"01/01/2020","endDate":"31/12/2020","obs":"Sin observaciones","link":"No","travelExpenses":"","activated":"SÍ","fullName":"LEONARDO ARIEL MUÑOZ VERGARA","slug":"leonardo_ariel_muñoz_vergara","month":8}}}}