{"carla_scarlett_caimapo_garrido":{"2017":{"3":{"camino":"/Salud/2017/Marzo","organismo_nombre":"Corporación Municipal de Ancud","organismo_codigo":"CM024","fecha_publicacion":"2021/07/08","anyo":2017,"Mes":"Marzo","Tipo Estamento":"Otros profesionales (Ley 19.378)","Nombres":"CARLA SCARLETT","Paterno":"CAIMAPO","Materno":"GARRIDO","grado_eus":"B15","tipo_calificacionp":"B","Tipo cargo":"B","region":"Región de Los Lagos","asignaciones":"(01)","Tipo Unidad monetaria":"Pesos","remuneracionbruta_mensual":855238,"remuliquida_mensual":706341,"Pago extra diurnas":0,"Horas extra diurnas":0,"Pago extra nocturnas":0,"Horas extra nocturnas":0,"Pago extra festivas":0,"Horas extra festivas":0,"fecha_ingreso":"01/03/2017","fecha_termino":"03/04/2017","observaciones":"Sin Observaciones","enlace":"No","viaticos":"","activado":"SÍ"},"4":{"camino":"/Salud/2017/Abril","organismo_nombre":"Corporación Municipal de Ancud","organismo_codigo":"CM024","fecha_publicacion":"2021/07/08","anyo":2017,"Mes":"Abril","Tipo Estamento":"Otros profesionales (Ley 19.378)","Nombres":"CARLA SCARLETT","Paterno":"CAIMAPO","Materno":"GARRIDO","grado_eus":"B15","tipo_calificacionp":"B","Tipo cargo":"B","region":"Región de Los Lagos","asignaciones":"(06)","Tipo Unidad monetaria":"Pesos","remuneracionbruta_mensual":899801,"remuliquida_mensual":743146,"Pago extra diurnas":0,"Horas extra diurnas":0,"Pago extra nocturnas":0,"Horas extra nocturnas":0,"Pago extra festivas":0,"Horas extra festivas":0,"fecha_ingreso":"01/03/2017","fecha_termino":"26/06/2017","observaciones":"Sin Observaciones","enlace":"No","viaticos":"","activado":"SÍ"},"5":{"camino":"/Salud/2017/Mayo","organismo_nombre":"Corporación Municipal de Ancud","organismo_codigo":"CM024","fecha_publicacion":"2021/07/08","anyo":2017,"Mes":"Mayo","Tipo Estamento":"Otros profesionales (Ley 19.378)","Nombres":"CARLA SCARLETT","Paterno":"CAIMAPO","Materno":"GARRIDO","grado_eus":"B15","tipo_calificacionp":"B","Tipo cargo":"B","region":"Región de Los Lagos","asignaciones":"(146)","Tipo Unidad monetaria":"Pesos","remuneracionbruta_mensual":931497,"remuliquida_mensual":769323,"Pago extra diurnas":0,"Horas extra diurnas":0,"Pago extra nocturnas":0,"Horas extra nocturnas":0,"Pago extra festivas":0,"Horas extra festivas":0,"fecha_ingreso":"01/03/2017","fecha_termino":"26/06/2017","observaciones":"Sin Observaciones","enlace":"No","viaticos":"","activado":"SÍ"},"6":{"camino":"/Salud/2017/Junio","organismo_nombre":"Corporación Municipal de Ancud","organismo_codigo":"CM024","fecha_publicacion":"2021/07/08","anyo":2017,"Mes":"Junio","Tipo Estamento":"Otros profesionales (Ley 19.378)","Nombres":"CARLA SCARLETT","Paterno":"CAIMAPO","Materno":"GARRIDO","grado_eus":"B15","tipo_calificacionp":"B","Tipo cargo":"B","region":"Región de Los Lagos","asignaciones":"(43)","Tipo Unidad monetaria":"Pesos","remuneracionbruta_mensual":1024119,"remuliquida_mensual":857598,"Pago extra diurnas":0,"Horas extra diurnas":0,"Pago extra nocturnas":0,"Horas extra nocturnas":0,"Pago extra festivas":0,"Horas extra festivas":0,"fecha_ingreso":"01/03/2017","fecha_termino":"26/06/2017","observaciones":"Sin Observaciones","enlace":"No","viaticos":"","activado":"SÍ"},"7":{"camino":"/Salud/2017/Julio","organismo_nombre":"Corporación Municipal de Ancud","organismo_codigo":"CM024","fecha_publicacion":"2021/07/08","anyo":2017,"Mes":"Julio","Tipo Estamento":"Otros profesionales (Ley 19.378)","Nombres":"CARLA SCARLETT","Paterno":"CAIMAPO","Materno":"GARRIDO","grado_eus":"B15","tipo_calificacionp":"B","Tipo cargo":"B","region":"Región de Los Lagos","asignaciones":"(122)","Tipo Unidad monetaria":"Pesos","remuneracionbruta_mensual":834330,"remuliquida_mensual":686022,"Pago extra diurnas":0,"Horas extra diurnas":0,"Pago extra nocturnas":0,"Horas extra nocturnas":0,"Pago extra festivas":0,"Horas extra festivas":0,"fecha_ingreso":"01/03/2017","fecha_termino":"07/08/2017","observaciones":"Sin Observaciones","enlace":"No","viaticos":"","activado":"SÍ"},"8":{"camino":"/Salud/2017/Agosto","organismo_nombre":"Corporación Municipal de Ancud","organismo_codigo":"CM024","fecha_publicacion":"2021/07/08","anyo":2017,"Mes":"Agosto","Tipo Estamento":"Otros profesionales (Ley 19.378)","Nombres":"CARLA SCARLETT","Paterno":"CAIMAPO","Materno":"GARRIDO","grado_eus":"B15","tipo_calificacionp":"B","Tipo cargo":"B","region":"Región de Los Lagos","asignaciones":"(122)","Tipo Unidad monetaria":"Pesos","remuneracionbruta_mensual":634945,"remuliquida_mensual":524401,"Pago extra diurnas":0,"Horas extra diurnas":0,"Pago extra nocturnas":0,"Horas extra nocturnas":0,"Pago extra festivas":0,"Horas extra festivas":0,"fecha_ingreso":"01/08/2017","fecha_termino":"22/08/2017","observaciones":"Sin Observaciones","enlace":"No","viaticos":"","activado":"SÍ"},"9":{"camino":"/Salud/2017/Septiembre","organismo_nombre":"Corporación Municipal de Ancud","organismo_codigo":"CM024","fecha_publicacion":"2021/07/08","anyo":2017,"Mes":"Septiembre","Tipo Estamento":"Otros profesionales (Ley 19.378)","Nombres":"CARLA SCARLETT","Paterno":"CAIMAPO","Materno":"GARRIDO","grado_eus":"B15","tipo_calificacionp":"B","Tipo cargo":"B","region":"Región de Los Lagos","asignaciones":"(01)","Tipo Unidad monetaria":"Pesos","remuneracionbruta_mensual":641238,"remuliquida_mensual":535114,"Pago extra diurnas":0,"Horas extra diurnas":0,"Pago extra nocturnas":0,"Horas extra nocturnas":0,"Pago extra festivas":0,"Horas extra festivas":0,"fecha_ingreso":"01/08/2017","fecha_termino":"30/11/2017","observaciones":"Sin Observaciones","enlace":"No","viaticos":"","activado":"SÍ"},"10":{"camino":"/Salud/2017/Octubre","organismo_nombre":"Corporación Municipal de Ancud","organismo_codigo":"CM024","fecha_publicacion":"2021/07/08","anyo":2017,"Mes":"Octubre","Tipo Estamento":"Otros profesionales (Ley 19.378)","Nombres":"CARLA SCARLETT","Paterno":"CAIMAPO","Materno":"GARRIDO","grado_eus":"B15","tipo_calificacionp":"B","Tipo cargo":"B","region":"Región de Los Lagos","asignaciones":"(43)","Tipo Unidad monetaria":"Pesos","remuneracionbruta_mensual":450189,"remuliquida_mensual":371811,"Pago extra diurnas":0,"Horas extra diurnas":0,"Pago extra nocturnas":0,"Horas extra nocturnas":0,"Pago extra festivas":0,"Horas extra festivas":0,"fecha_ingreso":"01/08/2017","fecha_termino":"30/11/2017","observaciones":"Sin Observaciones","enlace":"No","viaticos":"","activado":"SÍ"},"11":{"camino":"/Salud/2017/Noviembre","organismo_nombre":"Corporación Municipal de Ancud","organismo_codigo":"CM024","fecha_publicacion":"2021/07/08","anyo":2017,"Mes":"Noviembre","Tipo Estamento":"Otros profesionales (Ley 19.378)","Nombres":"CARLA SCARLETT","Paterno":"CAIMAPO","Materno":"GARRIDO","grado_eus":"B15","tipo_calificacionp":"B","Tipo cargo":"B","region":"Región de Los Lagos","asignaciones":"(01)","Tipo Unidad monetaria":"Pesos","remuneracionbruta_mensual":616486,"remuliquida_mensual":509155,"Pago extra diurnas":0,"Horas extra diurnas":0,"Pago extra nocturnas":0,"Horas extra nocturnas":0,"Pago extra festivas":0,"Horas extra festivas":0,"fecha_ingreso":"01/08/2017","fecha_termino":"30/11/2017","observaciones":"Sin observaciones","enlace":"No","viaticos":"","activado":"SÍ"},"12":{"camino":"/Salud/2017/Diciembre","organismo_nombre":"Corporación Municipal de Ancud","organismo_codigo":"CM024","fecha_publicacion":"2021/07/08","anyo":2017,"Mes":"Diciembre","Tipo Estamento":"Otros profesionales (Ley 19.378)","Nombres":"CARLA SCARLETT","Paterno":"CAIMAPO","Materno":"GARRIDO","grado_eus":"B15","tipo_calificacionp":"B","Tipo cargo":"B","region":"Región de Los Lagos","asignaciones":"(43)(20)","Tipo Unidad monetaria":"Pesos","remuneracionbruta_mensual":693305,"remuliquida_mensual":597923,"Pago extra diurnas":0,"Horas extra diurnas":0,"Pago extra nocturnas":0,"Horas extra nocturnas":0,"Pago extra festivas":0,"Horas extra festivas":0,"fecha_ingreso":"01/08/2017","fecha_termino":"31/12/2017","observaciones":"Sin Observaciones","enlace":"No","viaticos":"","activado":"SÍ"}},"2018":{"1":{"camino":"/Salud/2018/Enero","organismo_nombre":"Corporación Municipal de Ancud","organismo_codigo":"CM024","fecha_publicacion":"2021/07/08","anyo":2018,"Mes":"Enero","Tipo Estamento":"Otros profesionales (Ley 19.378)","Nombres":"CARLA SCARLETT","Paterno":"CAIMAPO","Materno":"GARRIDO","grado_eus":"B15","tipo_calificacionp":"B","Tipo cargo":"B","region":"Región de Los Lagos","asignaciones":"(01)","Tipo Unidad monetaria":"Pesos","remuneracionbruta_mensual":515402,"remuliquida_mensual":439092,"Pago extra diurnas":0,"Horas extra diurnas":0,"Pago extra nocturnas":0,"Horas extra nocturnas":0,"Pago extra festivas":0,"Horas extra festivas":0,"fecha_ingreso":"02/11/2017","fecha_termino":"07/11/2018","observaciones":"Sin Observaciones","enlace":"No","viaticos":"","activado":"SÍ"},"2":{"camino":"/Salud/2018/Febrero","organismo_nombre":"Corporación Municipal de Ancud","organismo_codigo":"CM024","fecha_publicacion":"2021/07/08","anyo":2018,"Mes":"Febrero","Tipo Estamento":"Otros profesionales (Ley 19.378)","Nombres":"CARLA SCARLETT","Paterno":"CAIMAPO","Materno":"GARRIDO","grado_eus":"B15","tipo_calificacionp":"B","Tipo cargo":"B","region":"Región de Los Lagos","asignaciones":"(43)","Tipo Unidad monetaria":"Pesos","remuneracionbruta_mensual":456572,"remuliquida_mensual":377083,"Pago extra diurnas":0,"Horas extra diurnas":0,"Pago extra nocturnas":0,"Horas extra nocturnas":0,"Pago extra festivas":0,"Horas extra festivas":0,"fecha_ingreso":"02/11/2017","fecha_termino":"07/11/2018","observaciones":"Sin Observaciones","enlace":"No","viaticos":"","activado":"SÍ"},"3":{"camino":"/Salud/2018/Marzo","organismo_nombre":"Corporación Municipal de Ancud","organismo_codigo":"CM024","fecha_publicacion":"2021/07/08","anyo":2018,"Mes":"Marzo","Tipo Estamento":"Otros profesionales (Ley 19.378)","Nombres":"CARLA SCARLETT","Paterno":"CAIMAPO","Materno":"GARRIDO","grado_eus":"B15","tipo_calificacionp":"B","Tipo cargo":"B","region":"Región de Los Lagos","asignaciones":"(01)","Tipo Unidad monetaria":"Pesos","remuneracionbruta_mensual":1015927,"remuliquida_mensual":839689,"Pago extra diurnas":0,"Horas extra diurnas":0,"Pago extra nocturnas":0,"Horas extra nocturnas":0,"Pago extra festivas":0,"Horas extra festivas":0,"fecha_ingreso":"02/11/2017","fecha_termino":"07/11/2018","observaciones":"Sin Observaciones","enlace":"No","viaticos":"","activado":"SÍ"},"4":{"camino":"/Salud/2018/Abril","organismo_nombre":"Corporación Municipal de Ancud","organismo_codigo":"CM024","fecha_publicacion":"2021/07/08","anyo":2018,"Mes":"Abril","Tipo Estamento":"Otros profesionales (Ley 19.378)","Nombres":"CARLA SCARLETT","Paterno":"CAIMAPO","Materno":"GARRIDO","grado_eus":"B15","tipo_calificacionp":"B","Tipo cargo":"B","region":"Región de Los Ríos","asignaciones":"(01)","Tipo Unidad monetaria":"Pesos","remuneracionbruta_mensual":1149953,"remuliquida_mensual":944896,"Pago extra diurnas":0,"Horas extra diurnas":0,"Pago extra nocturnas":0,"Horas extra nocturnas":0,"Pago extra festivas":0,"Horas extra festivas":0,"fecha_ingreso":"02/11/2017","fecha_termino":"07/11/2018","observaciones":"Sin Observaciones","enlace":"No","viaticos":"","activado":"SÍ"},"5":{"camino":"/Salud/2018/Mayo","organismo_nombre":"Corporación Municipal de Ancud","organismo_codigo":"CM024","fecha_publicacion":"2021/07/08","anyo":2018,"Mes":"Mayo","Tipo Estamento":"Otros profesionales (Ley 19.378)","Nombres":"CARLA SCARLETT","Paterno":"CAIMAPO","Materno":"GARRIDO","grado_eus":"B15","tipo_calificacionp":"B","Tipo cargo":"B","region":"Región de Los Lagos","asignaciones":"(01)","Tipo Unidad monetaria":"Pesos","remuneracionbruta_mensual":825566,"remuliquida_mensual":672213,"Pago extra diurnas":0,"Horas extra diurnas":0,"Pago extra nocturnas":0,"Horas extra nocturnas":0,"Pago extra festivas":0,"Horas extra festivas":0,"fecha_ingreso":"06/03/2018","fecha_termino":"30/06/2018","observaciones":"Sin Observaciones","enlace":"No","viaticos":"","activado":"SÍ"},"6":{"camino":"/Salud/2018/Junio","organismo_nombre":"Corporación Municipal de Ancud","organismo_codigo":"CM024","fecha_publicacion":"2021/07/08","anyo":2018,"Mes":"Junio","Tipo Estamento":"Otros profesionales (Ley 19.378)","Nombres":"CARLA SCARLETT","Paterno":"CAIMAPO","Materno":"GARRIDO","grado_eus":"B15","tipo_calificacionp":"B","Tipo cargo":"B","region":"Región de Los Lagos","asignaciones":"(01)","Tipo Unidad monetaria":"Pesos","remuneracionbruta_mensual":1501622,"remuliquida_mensual":1230055,"Pago extra diurnas":0,"Horas extra diurnas":0,"Pago extra nocturnas":0,"Horas extra nocturnas":0,"Pago extra festivas":0,"Horas extra festivas":0,"fecha_ingreso":"01/04/2018","fecha_termino":"17/07/2018","observaciones":"Sin Observaciones","enlace":"No","viaticos":"","activado":"SÍ"},"7":{"camino":"/Salud/2018/Julio","organismo_nombre":"Corporación Municipal de Ancud","organismo_codigo":"CM024","fecha_publicacion":"2021/07/08","anyo":2018,"Mes":"Julio","Tipo Estamento":"Otros profesionales (Ley 19.378)","Nombres":"CARLA SCARLETT","Paterno":"CAIMAPO","Materno":"GARRIDO","grado_eus":"B15","tipo_calificacionp":"B","Tipo cargo":"B","region":"Región de Los Lagos","asignaciones":"(01)","Tipo Unidad monetaria":"Pesos","remuneracionbruta_mensual":1151782,"remuliquida_mensual":946454,"Pago extra diurnas":0,"Horas extra diurnas":0,"Pago extra nocturnas":0,"Horas extra nocturnas":0,"Pago extra festivas":0,"Horas extra festivas":0,"fecha_ingreso":"01/04/2018","fecha_termino":"31/12/2018","observaciones":"Sin Observaciones","enlace":"No","viaticos":"","activado":"SÍ"},"8":{"camino":"/Salud/2018/Agosto","organismo_nombre":"Corporación Municipal de Ancud","organismo_codigo":"CM024","fecha_publicacion":"2021/07/08","anyo":2018,"Mes":"Agosto","Tipo Estamento":"Otros profesionales (Ley 19.378)","Nombres":"CARLA SCARLETT","Paterno":"CAIMAPO","Materno":"GARRIDO","grado_eus":"B15","tipo_calificacionp":"B","Tipo cargo":"B","region":"Región de Los Lagos","asignaciones":"(43)","Tipo Unidad monetaria":"Pesos","remuneracionbruta_mensual":483967,"remuliquida_mensual":396078,"Pago extra diurnas":0,"Horas extra diurnas":0,"Pago extra nocturnas":0,"Horas extra nocturnas":0,"Pago extra festivas":0,"Horas extra festivas":0,"fecha_ingreso":"01/04/2018","fecha_termino":"31/12/2018","observaciones":"Sin Observaciones","enlace":"No","viaticos":"","activado":"SÍ"},"9":{"camino":"/Salud/2018/Septiembre","organismo_nombre":"Corporación Municipal de Ancud","organismo_codigo":"CM024","fecha_publicacion":"2021/07/08","anyo":2018,"Mes":"Septiembre","Tipo Estamento":"Otros profesionales (Ley 19.378)","Nombres":"CARLA SCARLETT","Paterno":"CAIMAPO","Materno":"GARRIDO","grado_eus":"B15","tipo_calificacionp":"B","Tipo cargo":"B","region":"Región de Los Lagos","asignaciones":"(01)","Tipo Unidad monetaria":"Pesos","remuneracionbruta_mensual":597105,"remuliquida_mensual":500574,"Pago extra diurnas":0,"Horas extra diurnas":0,"Pago extra nocturnas":0,"Horas extra nocturnas":0,"Pago extra festivas":0,"Horas extra festivas":0,"fecha_ingreso":"01/04/2018","fecha_termino":"31/12/2018","observaciones":"Sin Observaciones","enlace":"No","viaticos":"","activado":"SÍ"},"10":{"camino":"/Salud/2018/Octubre","organismo_nombre":"Corporación Municipal de Ancud","organismo_codigo":"CM024","fecha_publicacion":"2021/07/08","anyo":2018,"Mes":"Octubre","Tipo Estamento":"Otros profesionales (Ley 19.378)","Nombres":"CARLA SCARLETT","Paterno":"CAIMAPO","Materno":"GARRIDO","grado_eus":"B15","tipo_calificacionp":"B","Tipo cargo":"B","region":"Región de Los Lagos","asignaciones":"(01)","Tipo Unidad monetaria":"Pesos","remuneracionbruta_mensual":438310,"remuliquida_mensual":358713,"Pago extra diurnas":0,"Horas extra diurnas":0,"Pago extra nocturnas":0,"Horas extra nocturnas":0,"Pago extra festivas":0,"Horas extra festivas":0,"fecha_ingreso":"01/04/2018","fecha_termino":"31/12/2018","observaciones":"Sin Observaciones","enlace":"No","viaticos":"","activado":"SÍ"},"11":{"camino":"/Salud/2018/Noviembre","organismo_nombre":"Corporación Municipal de Ancud","organismo_codigo":"CM024","fecha_publicacion":"2021/07/08","anyo":2018,"Mes":"Noviembre","Tipo Estamento":"Otros profesionales (Ley 19.378)","Nombres":"CARLA SCARLETT","Paterno":"CAIMAPO","Materno":"GARRIDO","grado_eus":"B15","tipo_calificacionp":"B","Tipo cargo":"B","region":"Región de Los Lagos","asignaciones":"(01)","Tipo Unidad monetaria":"Pesos","remuneracionbruta_mensual":438310,"remuliquida_mensual":358713,"Pago extra diurnas":0,"Horas extra diurnas":0,"Pago extra nocturnas":0,"Horas extra nocturnas":0,"Pago extra festivas":0,"Horas extra festivas":0,"fecha_ingreso":"01/04/2018","fecha_termino":"31/12/2018","observaciones":"Sin Observaciones","enlace":"No","viaticos":"","activado":"SÍ"},"12":{"camino":"/Salud/2018/Diciembre","organismo_nombre":"Corporación Municipal de Ancud","organismo_codigo":"CM024","fecha_publicacion":"2021/07/08","anyo":2018,"Mes":"Diciembre","Tipo Estamento":"Otros profesionales (Ley 19.378)","Nombres":"CARLA SCARLETT","Paterno":"CAIMAPO","Materno":"GARRIDO","grado_eus":"B15","tipo_calificacionp":"B","Tipo cargo":"B","region":"Región de Los Lagos","asignaciones":"(24)","Tipo Unidad monetaria":"Pesos","remuneracionbruta_mensual":957244,"remuliquida_mensual":830303,"Pago extra diurnas":0,"Horas extra diurnas":0,"Pago extra nocturnas":0,"Horas extra nocturnas":0,"Pago extra festivas":0,"Horas extra festivas":0,"fecha_ingreso":"01/04/2018","fecha_termino":"31/12/2019","observaciones":"Sin Observaciones","enlace":"No","viaticos":"","activado":"SÍ"}},"2019":{"1":{"camino":"/Salud/2019/Enero","organismo_nombre":"Corporación Municipal de Ancud","organismo_codigo":"CM024","fecha_publicacion":"2021/07/08","anyo":2019,"Mes":"Enero","Tipo Estamento":"Otros profesionales (Ley 19.378)","Nombres":"CARLA SCARLETT","Paterno":"CAIMAPO","Materno":"GARRIDO","grado_eus":"B15","tipo_calificacionp":"B","Tipo cargo":"B","region":"Región de Los Lagos","asignaciones":"(43)","Tipo Unidad monetaria":"Pesos","remuneracionbruta_mensual":591552,"remuliquida_mensual":500736,"Pago extra diurnas":0,"Horas extra diurnas":0,"Pago extra nocturnas":0,"Horas extra nocturnas":0,"Pago extra festivas":0,"Horas extra festivas":0,"fecha_ingreso":"01/04/2018","fecha_termino":"31/12/2019","observaciones":"Sin Observaciones","enlace":"No","viaticos":"","activado":"SÍ"},"2":{"camino":"/Salud/2019/Febrero","organismo_nombre":"Corporación Municipal de Ancud","organismo_codigo":"CM024","fecha_publicacion":"2021/07/08","anyo":2019,"Mes":"Febrero","Tipo Estamento":"Otros profesionales (Ley 19.378)","Nombres":"CARLA SCARLETT","Paterno":"CAIMAPO","Materno":"GARRIDO","grado_eus":"B15","tipo_calificacionp":"B","Tipo cargo":"B","region":"Región de Los Lagos","asignaciones":"(43)","Tipo Unidad monetaria":"Pesos","remuneracionbruta_mensual":472552,"remuliquida_mensual":386736,"Pago extra diurnas":0,"Horas extra diurnas":0,"Pago extra nocturnas":0,"Horas extra nocturnas":0,"Pago extra festivas":0,"Horas extra festivas":0,"fecha_ingreso":"01/04/2018","fecha_termino":"31/12/2019","observaciones":"Sin Observaciones","enlace":"No","viaticos":"","activado":"SÍ"},"3":{"camino":"/Salud/2019/Marzo","organismo_nombre":"Corporación Municipal de Ancud","organismo_codigo":"CM024","fecha_publicacion":"2021/07/08","anyo":2019,"Mes":"Marzo","Tipo Estamento":"Otros profesionales (Ley 19.378)","Nombres":"CARLA SCARLETT","Paterno":"CAIMAPO","Materno":"GARRIDO","grado_eus":"B14","tipo_calificacionp":"B","Tipo cargo":"B","region":"Región de Los Lagos","asignaciones":"(43)","Tipo Unidad monetaria":"Pesos","remuneracionbruta_mensual":639760,"remuliquida_mensual":527116,"Pago extra diurnas":0,"Horas extra diurnas":0,"Pago extra nocturnas":0,"Horas extra nocturnas":0,"Pago extra festivas":0,"Horas extra festivas":0,"fecha_ingreso":"01/04/2018","fecha_termino":"31/12/2019","observaciones":"Sin observaciones","enlace":"No","viaticos":"","activado":"SÍ"},"4":{"camino":"/Salud/2019/Abril","organismo_nombre":"Corporación Municipal de Ancud","organismo_codigo":"CM024","fecha_publicacion":"2021/07/08","anyo":2019,"Mes":"Abril","Tipo Estamento":"Otros profesionales (Ley 19.378)","Nombres":"CARLA SCARLETT","Paterno":"CAIMAPO","Materno":"GARRIDO","grado_eus":"B14","tipo_calificacionp":"B","Tipo cargo":"B","region":"Región de Los Lagos","asignaciones":"(43)","Tipo Unidad monetaria":"Pesos","remuneracionbruta_mensual":787311,"remuliquida_mensual":644335,"Pago extra diurnas":0,"Horas extra diurnas":0,"Pago extra nocturnas":0,"Horas extra nocturnas":0,"Pago extra festivas":0,"Horas extra festivas":0,"fecha_ingreso":"01/04/2018","fecha_termino":"31/12/2019","observaciones":"Sin Observaciones","enlace":"No","viaticos":"","activado":"SÍ"},"5":{"camino":"/Salud/2019/Mayo","organismo_nombre":"Corporación Municipal de Ancud","organismo_codigo":"CM024","fecha_publicacion":"2021/07/08","anyo":2019,"Mes":"Mayo","Tipo Estamento":"Otros profesionales (Ley 19.378)","Nombres":"CARLA SCARLETT","Paterno":"CAIMAPO","Materno":"GARRIDO","grado_eus":"B15","tipo_calificacionp":"B","Tipo cargo":"B","region":"Región de Los Lagos","asignaciones":"(43)(43)","Tipo Unidad monetaria":"Pesos","remuneracionbruta_mensual":765084,"remuliquida_mensual":626145,"Pago extra diurnas":0,"Horas extra diurnas":0,"Pago extra nocturnas":0,"Horas extra nocturnas":0,"Pago extra festivas":0,"Horas extra festivas":0,"fecha_ingreso":"01/04/2018","fecha_termino":"31/12/2019","observaciones":"Sin observaciones","enlace":"No","viaticos":"","activado":"SÍ"},"6":{"camino":"/Salud/2019/Junio","organismo_nombre":"Corporación Municipal de Ancud","organismo_codigo":"CM024","fecha_publicacion":"2021/07/08","anyo":2019,"Mes":"Junio","Tipo Estamento":"Otros profesionales (Ley 19.378)","Nombres":"CARLA SCARLETT","Paterno":"CAIMAPO","Materno":"GARRIDO","grado_eus":"B15","tipo_calificacionp":"B","Tipo cargo":"B","region":"Región de Los Lagos","asignaciones":"(43)(43)","Tipo Unidad monetaria":"Pesos","remuneracionbruta_mensual":1350773,"remuliquida_mensual":1059113,"Pago extra diurnas":0,"Horas extra diurnas":0,"Pago extra nocturnas":0,"Horas extra nocturnas":0,"Pago extra festivas":0,"Horas extra festivas":0,"fecha_ingreso":"01/04/2018","fecha_termino":"31/12/2019","observaciones":"Sin observaciones","enlace":"No","viaticos":"","activado":"SÍ"},"7":{"camino":"/Salud/2019/Julio","organismo_nombre":"Corporación Municipal de Ancud","organismo_codigo":"CM024","fecha_publicacion":"2021/07/08","anyo":2019,"Mes":"Julio","Tipo Estamento":"Otros profesionales (Ley 19.378)","Nombres":"CARLA SCARLETT","Paterno":"CAIMAPO","Materno":"GARRIDO","grado_eus":"B15","tipo_calificacionp":"B","Tipo cargo":"B","region":"Región de Los Lagos","asignaciones":"(43)(43)","Tipo Unidad monetaria":"Pesos","remuneracionbruta_mensual":749332,"remuliquida_mensual":607246,"Pago extra diurnas":0,"Horas extra diurnas":0,"Pago extra nocturnas":0,"Horas extra nocturnas":0,"Pago extra festivas":0,"Horas extra festivas":0,"fecha_ingreso":"01/04/2018","fecha_termino":"31/12/2019","observaciones":"Sin observaciones","enlace":"No","viaticos":"","activado":"SÍ"},"8":{"camino":"/Salud/2019/Agosto","organismo_nombre":"Corporación Municipal de Ancud","organismo_codigo":"CM024","fecha_publicacion":"2021/07/08","anyo":2019,"Mes":"Agosto","Tipo Estamento":"Otros profesionales (Ley 19.378)","Nombres":"CARLA SCARLETT","Paterno":"CAIMAPO","Materno":"GARRIDO","grado_eus":"B14","tipo_calificacionp":"B","Tipo cargo":"B","region":"Región de Los Lagos","asignaciones":"(43)","Tipo Unidad monetaria":"Pesos","remuneracionbruta_mensual":770425,"remuliquida_mensual":603265,"Pago extra diurnas":0,"Horas extra diurnas":0,"Pago extra nocturnas":0,"Horas extra nocturnas":0,"Pago extra festivas":0,"Horas extra festivas":0,"fecha_ingreso":"01/04/2018","fecha_termino":"31/12/2019","observaciones":"Sin observaciones","enlace":"No","viaticos":"","activado":"SÍ"},"9":{"camino":"/Salud/2019/Septiembre","organismo_nombre":"Corporación Municipal de Ancud","organismo_codigo":"CM024","fecha_publicacion":"2021/07/08","anyo":2019,"Mes":"Septiembre","Tipo Estamento":"Otros profesionales (Ley 19.378)","Nombres":"CARLA SCARLETT","Paterno":"CAIMAPO","Materno":"GARRIDO","grado_eus":"B14","tipo_calificacionp":"B","Tipo cargo":"B","region":"Región de Los Lagos","asignaciones":"(43)","Tipo Unidad monetaria":"Pesos","remuneracionbruta_mensual":1441106,"remuliquida_mensual":1177583,"Pago extra diurnas":0,"Horas extra diurnas":0,"Pago extra nocturnas":0,"Horas extra nocturnas":0,"Pago extra festivas":0,"Horas extra festivas":0,"fecha_ingreso":"01/04/2018","fecha_termino":"31/12/2019","observaciones":"Sin observaciones","enlace":"No","viaticos":"","activado":"SÍ"},"10":{"camino":"/Salud/2019/Octubre","organismo_nombre":"Corporación Municipal de Ancud","organismo_codigo":"CM024","fecha_publicacion":"2021/07/08","anyo":2019,"Mes":"Octubre","Tipo Estamento":"Otros profesionales (Ley 19.378)","Nombres":"CARLA SCARLETT","Paterno":"CAIMAPO","Materno":"GARRIDO","grado_eus":"B14","tipo_calificacionp":"B","Tipo cargo":"B","region":"Región de Los Lagos","asignaciones":"(43)","Tipo Unidad monetaria":"Pesos","remuneracionbruta_mensual":770425,"remuliquida_mensual":624339,"Pago extra diurnas":0,"Horas extra diurnas":0,"Pago extra nocturnas":0,"Horas extra nocturnas":0,"Pago extra festivas":0,"Horas extra festivas":0,"fecha_ingreso":"01/04/2018","fecha_termino":"31/12/2019","observaciones":"Sin Observaciones","enlace":"No","viaticos":"","activado":"SÍ"},"11":{"camino":"/Salud/2019/Noviembre","organismo_nombre":"Corporación Municipal de Ancud","organismo_codigo":"CM024","fecha_publicacion":"2021/07/08","anyo":2019,"Mes":"Noviembre","Tipo Estamento":"Otros profesionales (Ley 19.378)","Nombres":"CARLA SCARLETT","Paterno":"CAIMAPO","Materno":"GARRIDO","grado_eus":"B14","tipo_calificacionp":"B","Tipo cargo":"B","region":"Región de Los Lagos","asignaciones":"(43)(43)","Tipo Unidad monetaria":"Pesos","remuneracionbruta_mensual":1015101,"remuliquida_mensual":820148,"Pago extra diurnas":0,"Horas extra diurnas":0,"Pago extra nocturnas":0,"Horas extra nocturnas":0,"Pago extra festivas":0,"Horas extra festivas":0,"fecha_ingreso":"01/04/2018","fecha_termino":"31/12/2019","observaciones":"Sin observaciones","enlace":"No","viaticos":"","activado":"SÍ"},"12":{"camino":"/Salud/2019/Diciembre","organismo_nombre":"Corporación Municipal de Ancud","organismo_codigo":"CM024","fecha_publicacion":"2021/07/08","anyo":2019,"Mes":"Diciembre","Tipo Estamento":"Otros profesionales (Ley 19.378)","Nombres":"CARLA SCARLETT","Paterno":"CAIMAPO","Materno":"GARRIDO","grado_eus":"B14","tipo_calificacionp":"B","Tipo cargo":"B","region":"Región de Los Lagos","asignaciones":"(43)(24)","Tipo Unidad monetaria":"Pesos","remuneracionbruta_mensual":1707210,"remuliquida_mensual":1421915,"Pago extra diurnas":0,"Horas extra diurnas":0,"Pago extra nocturnas":0,"Horas extra nocturnas":0,"Pago extra festivas":0,"Horas extra festivas":0,"fecha_ingreso":"01/04/2018","fecha_termino":"31/12/2019","observaciones":"Sin observaciones","enlace":"No","viaticos":"","activado":"SÍ"}},"2020":{"1":{"camino":"/Salud/2020/Enero","organismo_nombre":"Corporación Municipal de Ancud","organismo_codigo":"CM024","fecha_publicacion":"2021/07/08","anyo":2020,"Mes":"Enero","Tipo Estamento":"Otros profesionales (Ley 19.378)","Nombres":"CARLA SCARLETT","Paterno":"CAIMAPO","Materno":"GARRIDO","grado_eus":"B14","tipo_calificacionp":"B","Tipo cargo":"B","region":"Región de Los Lagos","asignaciones":"(01)","Tipo Unidad monetaria":"Pesos","remuneracionbruta_mensual":873938,"remuliquida_mensual":729079,"Pago extra diurnas":0,"Horas extra diurnas":0,"Pago extra nocturnas":0,"Horas extra nocturnas":0,"Pago extra festivas":0,"Horas extra festivas":0,"fecha_ingreso":"01/04/2018","fecha_termino":"30/06/2020","observaciones":"Sin observaciones","enlace":"No","viaticos":"","activado":"SÍ"},"2":{"camino":"/Salud/2020/Febrero","organismo_nombre":"Corporación Municipal de Ancud","organismo_codigo":"CM024","fecha_publicacion":"2021/07/08","anyo":2020,"Mes":"Febrero","Tipo Estamento":"Otros profesionales (Ley 19.378)","Nombres":"CARLA SCARLETT","Paterno":"CAIMAPO","Materno":"GARRIDO","grado_eus":"B14","tipo_calificacionp":"B","Tipo cargo":"B","region":"Región de Los Lagos","asignaciones":"(01)","Tipo Unidad monetaria":"Pesos","remuneracionbruta_mensual":751606,"remuliquida_mensual":606747,"Pago extra diurnas":0,"Horas extra diurnas":0,"Pago extra nocturnas":0,"Horas extra nocturnas":0,"Pago extra festivas":0,"Horas extra festivas":0,"fecha_ingreso":"01/04/2018","fecha_termino":"30/06/2020","observaciones":"Sin observaciones","enlace":"No","viaticos":"","activado":"SÍ"},"3":{"camino":"/Salud/2020/Marzo","organismo_nombre":"Corporación Municipal de Ancud","organismo_codigo":"CM024","fecha_publicacion":"2021/07/08","anyo":2020,"Mes":"Marzo","Tipo Estamento":"Otros profesionales (Ley 19.378)","Nombres":"CARLA SCARLETT","Paterno":"CAIMAPO","Materno":"GARRIDO","grado_eus":"B14","tipo_calificacionp":"B","Tipo cargo":"B","region":"Región de Los Lagos","asignaciones":"(01)","Tipo Unidad monetaria":"Pesos","remuneracionbruta_mensual":928539,"remuliquida_mensual":729216,"Pago extra diurnas":0,"Horas extra diurnas":0,"Pago extra nocturnas":0,"Horas extra nocturnas":0,"Pago extra festivas":0,"Horas extra festivas":0,"fecha_ingreso":"01/04/2018","fecha_termino":"30/06/2020","observaciones":"Sin observaciones","enlace":"No","viaticos":"","activado":"SÍ"},"4":{"camino":"/Salud/2020/Abril","organismo_nombre":"Corporación Municipal de Ancud","organismo_codigo":"CM024","fecha_publicacion":"2021/07/08","anyo":2020,"Mes":"Abril","Tipo Estamento":"Otros profesionales (Ley 19.378)","Nombres":"CARLA SCARLETT","Paterno":"CAIMAPO","Materno":"GARRIDO","grado_eus":"B14","tipo_calificacionp":"B","Tipo cargo":"B","region":"Región de Los Lagos","asignaciones":"(01)","Tipo Unidad monetaria":"Pesos","remuneracionbruta_mensual":1174507,"remuliquida_mensual":945478,"Pago extra diurnas":0,"Horas extra diurnas":0,"Pago extra nocturnas":0,"Horas extra nocturnas":0,"Pago extra festivas":0,"Horas extra festivas":0,"fecha_ingreso":"01/04/2018","fecha_termino":"30/06/2020","observaciones":"Sin observaciones","enlace":"No","viaticos":"","activado":"SÍ"},"5":{"camino":"/Salud/2020/Mayo","organismo_nombre":"Corporación Municipal de Ancud","organismo_codigo":"CM024","fecha_publicacion":"2021/07/08","anyo":2020,"Mes":"Mayo","Tipo Estamento":"Otros profesionales (Ley 19.378)","Nombres":"CARLA SCARLETT","Paterno":"CAIMAPO","Materno":"GARRIDO","grado_eus":"B14","tipo_calificacionp":"B","Tipo cargo":"B","region":"Región de Los Lagos","asignaciones":"(01)","Tipo Unidad monetaria":"Pesos","remuneracionbruta_mensual":751606,"remuliquida_mensual":585107,"Pago extra diurnas":0,"Horas extra diurnas":0,"Pago extra nocturnas":0,"Horas extra nocturnas":0,"Pago extra festivas":0,"Horas extra festivas":0,"fecha_ingreso":"01/04/2018","fecha_termino":"30/06/2020","observaciones":"Sin observaciones","enlace":"No","viaticos":"","activado":"SÍ"},"6":{"camino":"/Salud/2020/Junio","organismo_nombre":"Corporación Municipal de Ancud","organismo_codigo":"CM024","fecha_publicacion":"2021/07/08","anyo":2020,"Mes":"Junio","Tipo Estamento":"Otros profesionales (Ley 19.378)","Nombres":"CARLA SCARLETT","Paterno":"CAIMAPO","Materno":"GARRIDO","grado_eus":"B14","tipo_calificacionp":"B","Tipo cargo":"B","region":"Región de Los Lagos","asignaciones":"(01)","Tipo Unidad monetaria":"Pesos","remuneracionbruta_mensual":1382739,"remuliquida_mensual":1110140,"Pago extra diurnas":0,"Horas extra diurnas":0,"Pago extra nocturnas":0,"Horas extra nocturnas":0,"Pago extra festivas":0,"Horas extra festivas":0,"fecha_ingreso":"01/04/2018","fecha_termino":"30/06/2020","observaciones":"Sin observaciones","enlace":"No","viaticos":"","activado":"SÍ"},"7":{"camino":"/Salud/2020/Julio","organismo_nombre":"Corporación Municipal de Ancud","organismo_codigo":"CM024","fecha_publicacion":"2021/07/08","anyo":2020,"Mes":"Julio","Tipo Estamento":"Otros profesionales (Ley 19.378)","Nombres":"CARLA SCARLETT","Paterno":"CAIMAPO","Materno":"GARRIDO","grado_eus":"B14","tipo_calificacionp":"B","Tipo cargo":"B","region":"Región de Los Lagos","asignaciones":"(01)","Tipo Unidad monetaria":"Pesos","remuneracionbruta_mensual":774153,"remuliquida_mensual":620948,"Pago extra diurnas":0,"Horas extra diurnas":0,"Pago extra nocturnas":0,"Horas extra nocturnas":0,"Pago extra festivas":0,"Horas extra festivas":0,"fecha_ingreso":"01/04/2018","fecha_termino":"30/09/2020","observaciones":"Sin observaciones","enlace":"No","viaticos":"","activado":"SÍ"}}}}