{"priscilla_katherine_galvez_hernandez":{"2018":{"1":{"internalPath":"/2018/Enero/CONTRATA TECNICO","institution":"Hospital Gustavo Fricke","institutionCode":"AO098","publicationDate":"2021/07/12","year":2018,"monthString":"Enero","contractType":"Técnico","name":"PRISCILLA KATHERINE","surname1":"GALVEZ","surname2":"HERNANDEZ","salaryGrade":23,"qualificationType":"TECNICO NIVEL SUPERIOR","position":"ATENCION CLINICA","region":"Región de Valparaíso","extraBenefits":"(01)","currency":"Pesos","salaryBeforeTaxes":0,"salaryAfterTaxes":"","bonusDayTime":0,"extraHoursDayTime":0,"bonusNightTime":0,"extraHoursNightTime":0,"bonusHolidays":"","extraHoursHolidays":"","startDate":"11/01/2018","endDate":"25/02/2018","obs":6,"link":"No","travelExpenses":"","activated":"SÍ","fullName":"PRISCILLA KATHERINE GALVEZ HERNANDEZ","slug":"priscilla_katherine_galvez_hernandez","month":1,"cleanFullName":"priscilla katherine galvez hernandez"},"2":{"internalPath":"/2018/Febrero/CONTRATA TECNICO","institution":"Hospital Gustavo Fricke","institutionCode":"AO098","publicationDate":"2021/07/12","year":2018,"monthString":"Febrero","contractType":"Técnico","name":"PRISCILLA KATHERINE","surname1":"GALVEZ","surname2":"HERNANDEZ","salaryGrade":23,"qualificationType":"TECNICO NIVEL SUPERIOR","position":"TEC. NIVEL SUP. ENFERMERIA","region":"Región de Valparaíso","extraBenefits":"(01)","currency":"Pesos","salaryBeforeTaxes":364668,"salaryAfterTaxes":"","bonusDayTime":0,"extraHoursDayTime":0,"bonusNightTime":0,"extraHoursNightTime":0,"bonusHolidays":"","extraHoursHolidays":"","startDate":"11/01/2018","endDate":"25/02/2018","obs":613,"link":"No","travelExpenses":"","activated":"SÍ","fullName":"PRISCILLA KATHERINE GALVEZ HERNANDEZ","slug":"priscilla_katherine_galvez_hernandez","month":2,"cleanFullName":"priscilla katherine galvez hernandez"},"3":{"internalPath":"/2018/Marzo/Contrata Técnico","institution":"Hospital Gustavo Fricke","institutionCode":"AO098","publicationDate":"2021/07/12","year":2018,"monthString":"Marzo","contractType":"Técnico","name":"PRISCILLA KATHERINE","surname1":"GALVEZ","surname2":"HERNANDEZ","salaryGrade":22,"qualificationType":"TECNICO NIVEL SUPERIOR","position":"TEC. NIVEL SUP. ENFERMERIA","region":"Región de Valparaíso","extraBenefits":"(01)","currency":"Pesos","salaryBeforeTaxes":482813,"salaryAfterTaxes":"","bonusDayTime":0,"extraHoursDayTime":0,"bonusNightTime":"","extraHoursNightTime":0,"bonusHolidays":"","extraHoursHolidays":"","startDate":"01/01/2018","endDate":"26/04/2018","obs":613,"link":"No","travelExpenses":"","activated":"SÍ","fullName":"PRISCILLA KATHERINE GALVEZ HERNANDEZ","slug":"priscilla_katherine_galvez_hernandez","month":3,"cleanFullName":"priscilla katherine galvez hernandez"},"4":{"internalPath":"/2018/Abril/Contrata Técnico","institution":"Hospital Gustavo Fricke","institutionCode":"AO098","publicationDate":"2021/07/12","year":2018,"monthString":"Abril","contractType":"Técnico","name":"PRISCILLA KATHERINE","surname1":"GALVEZ","surname2":"HERNANDEZ","salaryGrade":22,"qualificationType":"TECNICO NIVEL SUPERIOR","position":"ATENCION CLINICA","region":"Región de Valparaíso","extraBenefits":"(01)","currency":"Pesos","salaryBeforeTaxes":446712,"salaryAfterTaxes":"","bonusDayTime":0,"extraHoursDayTime":0,"bonusNightTime":0,"extraHoursNightTime":0,"bonusHolidays":"","extraHoursHolidays":"","startDate":"01/01/2018","endDate":"26/04/2018","obs":613,"link":"No","travelExpenses":"","activated":"SÍ","fullName":"PRISCILLA KATHERINE GALVEZ HERNANDEZ","slug":"priscilla_katherine_galvez_hernandez","month":4,"cleanFullName":"priscilla katherine galvez hernandez"}}}}